Workbook

Sheet Frontend from frontend
A1: Frontend UI file inventory from frontend/*
A3: 1 | B3: app/(auth)/login/page.tsx | C3: ="frontend/" & B3 -> frontend/app/(auth)/login/page.tsx
A4: =A3+1 -> 2 | B4: app/(auth)/register/page.tsx | C4: ="frontend/" & B4 -> frontend/app/(auth)/register/page.tsx
A5: =A4+1 -> 3 | B5: app/(auth)/forgot-password/page.tsx | C5: ="frontend/" & B5 -> frontend/app/(auth)/forgot-password/page.tsx
A6: =A5+1 -> 4 | B6: app/(auth)/reset-password/page.tsx | C6: ="frontend/" & B6 -> frontend/app/(auth)/reset-password/page.tsx
A7: =A6+1 -> 5 | B7: app/(auth)/verify-email/page.tsx | C7: ="frontend/" & B7 -> frontend/app/(auth)/verify-email/page.tsx
A8: =A7+1 -> 6 | B8: app/(auth)/verify-email/pending/page.tsx | C8: ="frontend/" & B8 -> frontend/app/(auth)/verify-email/pending/page.tsx
A9: =A8+1 -> 7 | B9: app/(auth)/verify-2fa/page.tsx | C9: ="frontend/" & B9 -> frontend/app/(auth)/verify-2fa/page.tsx
A10: =A9+1 -> 8 | B10: app/(auth)/layout.tsx | C10: ="frontend/" & B10 -> frontend/app/(auth)/layout.tsx
A11: =A10+1 -> 9 | B11: app/(auth)/loading.tsx | C11: ="frontend/" & B11 -> frontend/app/(auth)/loading.tsx
A12: =A11+1 -> 10 | B12: app/(marketing)/page.tsx | C12: ="frontend/" & B12 -> frontend/app/(marketing)/page.tsx
A13: =A12+1 -> 11 | B13: app/(marketing)/pricing/page.tsx | C13: ="frontend/" & B13 -> frontend/app/(marketing)/pricing/page.tsx
A14: =A13+1 -> 12 | B14: app/(marketing)/layout.tsx | C14: ="frontend/" & B14 -> frontend/app/(marketing)/layout.tsx
A15: =A14+1 -> 13 | B15: app/(marketing)/landing-content.tsx | C15: ="frontend/" & B15 -> frontend/app/(marketing)/landing-content.tsx
... A174: =A173+1 -> 172 | B174: components/ui/skeleton.tsx | C174: ="frontend/" & B174 -> frontend/components/ui/skeleton.tsx

Sheet Frontend from monolith
A1: Frontend UI file inventory from root directory (Monolith Architecture)
A3: NO. | B3: Part | C3: Paths and Filenames | D3: Interactive UI Element | E3: Readable UI Element
A4: ----- | B4: ------ | C4: --------------------- | D4: ------------------------ | E4: ---------------------
A5: 1 | B5: Part 05 | C5: app/(auth)/layout.tsx | E5: YES
A6: 2 | B6: Part 05 | C6: app/(auth)/login/page.tsx | D6: YES | E6: YES
A7: 3 | B7: Part 05 | C7: app/(auth)/register/page.tsx | D7: YES | E7: YES
A8: 4 | B8: Part 05 | C8: app/(auth)/verify-email/page.tsx | D8: YES | E8: YES
A9: 5 | B9: Part 05 | C9: app/(auth)/verify-email/pending/page.tsx | E9: YES
A10: 6 | B10: Part 05 | C10: app/(auth)/forgot-password/page.tsx | D10: YES | E10: YES
A11: 7 | B11: Part 05 | C11: app/(auth)/reset-password/page.tsx | D11: YES | E11: YES
A12: 8 | B12: Part 05 | C12: app/admin/login/page.tsx | D12: YES | E12: YES
A13: 9 | B13: Part 05 | C13: components/auth/register-form.tsx | D13: YES | E13: YES
A14: 10 | B14: Part 05 | C14: components/auth/login-form.tsx | D14: YES | E14: YES
A15: 11 | B15: Part 05 | C15: components/auth/social-auth-buttons.tsx | D15: YES
A16: 12 | B16: Part 08 | C16: app/(dashboard)/layout.tsx | D16: YES | E16: YES
A17: 13 | B17: Part 08 | C17: app/(dashboard)/dashboard/page.tsx | D17: YES | E17: YES
A18: 14 | B18: Part 08 | C18: app/(dashboard)/alerts/page.tsx | D18: YES | E18: YES
A19: 15 | B19: Part 08 | C19: app/(dashboard)/alerts/new/page.tsx | D19: YES | E19: YES
A20: 16 | B20: Part 08 | C20: app/(dashboard)/alerts/alerts-client.tsx | D20: YES | E20: YES
A21: 17 | B21: Part 08 | C21: app/(dashboard)/watchlist/page.tsx | D21: YES | E21: YES
A22: 18 | B22: Part 08 | C22: app/(dashboard)/watchlist/watchlist-client.tsx | D22: YES | E22: YES
A23: 19 | B23: Part 08 | C23: app/(dashboard)/charts/page.tsx | D23: YES | E23: YES
A24: 20 | B24: Part 08 | C24: app/(dashboard)/charts/[symbol]/[timeframe]/page.tsx | D24: YES | E24: YES
A25: 21 | B25: Part 08 | C25: app/(dashboard)/settings/layout.tsx | D25: YES | E25: YES
A26: 22 | B26: Part 08 | C26: app/(dashboard)/settings/page.tsx | D26: YES | E26: YES
A27: 23 | B27: Part 08 | C27: app/(dashboard)/settings/account/page.tsx | D27: YES | E27: YES
... A34: 30 | B34: Part 08 | C34: app/(dashboard)/settings/security/page.tsx | D34: YES | E34: YES
A35: 31 | B35: Part 08 | C35: app/(dashboard)/settings/terms/page.tsx | E35: YES
A36: 32 | B36: Part 08 | C36: app/(dashboard)/admin/page.tsx | D36: YES | E36: YES
A37: 33 | B37: Part 08 | C37: app/(dashboard)/admin/users/page.tsx | D37: YES | E37: YES
A38: 34 | B38: Part 08 | C38: app/(dashboard)/admin/fraud-alerts/page.tsx | D38: YES | E38: YES
A39: 35 | B39: Part 08 | C39: app/(dashboard)/admin/api-usage/page.tsx | D39: YES | E39: YES
A40: 36 | B40: Part 08 | C40: app/(dashboard)/admin/error-logs/page.tsx | D40: YES | E40: YES
A41: 37 | B41: Part 08 | C41: app/(dashboard)/admin/disbursements/page.tsx | D41: YES | E41: YES
A42: 38 | B42: Part 08 | C42: app/(dashboard)/admin/disbursements/accounts/page.tsx | D42: YES | E42: YES
A43: 39 | B43: Part 08 | C43: app/(dashboard)/admin/disbursements/affiliates/page.tsx | D43: YES | E43: YES
A44: 40 | B44: Part 08 | C44: app/(dashboard)/admin/disbursements/batches/page.tsx | D44: YES | E44: YES
A45: 41 | B45: Part 08 | C45: app/(dashboard)/admin/disbursements/transactions/page.tsx | D45: YES | E45: YES
A46: 42 | B46: Part 08 | C46: app/(dashboard)/admin/disbursements/audit-logs/page.tsx | D46: YES | E46: YES
A47: 43 | B47: Part 08 | C47: app/(dashboard)/admin/disbursements/config/page.tsx | D47: YES | E47: YES
... A50: 46 | B50: Part 08 | C50: app/(dashboard)/admin/disbursements/edit/[id]/page.tsx | D50: YES | E50: YES
A51: 47 | B51: Part 08 | C51: app/(dashboard)/admin/disbursements/preview/[id]/page.tsx | E51: YES
A52: 48 | B52: Part 08 | C52: components/dashboard/stats-card.tsx | E52: YES
A53: 49 | B53: Part 08 | C53: components/dashboard/recent-alerts.tsx | D53: YES | E53: YES
A54: 50 | B54: Part 08 | C54: components/dashboard/watchlist-widget.tsx | D54: YES | E54: YES
A55: 51 | B55: Part 08 | C55: components/dashboard/upgrade-prompt.tsx | D55: YES | E55: YES
A56: 52 | B56: Part 08 | C56: components/layout/header.tsx | D56: YES | E56: YES
A57: 53 | B57: Part 08 | C57: components/layout/sidebar.tsx | D57: YES | E57: YES
A58: 54 | B58: Part 08 | C58: components/layout/mobile-nav.tsx | D58: YES | E58: YES
A59: 55 | B59: Part 08 | C59: components/layout/footer.tsx | E59: YES
A60: 56 | B60: Part 09 | C60: app/(dashboard)/charts/[symbol]/[timeframe]/trading-chart-client.tsx | D60: YES | E60: YES
A61: 57 | B61: Part 09 | C61: components/charts/trading-chart.tsx | D61: YES | E61: YES
A62: 58 | B62: Part 09 | C62: components/charts/pro-indicator-overlay.tsx | D62: YES | E62: YES
A63: 59 | B63: Part 09 | C63: components/charts/indicator-toggles.tsx | D63: YES | E63: YES
A64: 60 | B64: Part 09 | C64: components/charts/chart-controls.tsx | D64: YES | E64: YES
A65: 61 | B65: Part 09 | C65: components/charts/timeframe-selector.tsx | D65: YES | E65: YES
A66: 62 | B66: Part 10 | C66: components/watchlist/symbol-selector.tsx | D66: YES | E66: YES
A67: 63 | B67: Part 10 | C67: components/watchlist/timeframe-grid.tsx | D67: YES | E67: YES
A68: 64 | B68: Part 10 | C68: components/watchlist/watchlist-item.tsx | D68: YES | E68: YES
A69: 65 | B69: Part 11 | C69: components/alerts/alert-card.tsx | D69: YES | E69: YES
A70: 66 | B70: Part 11 | C70: components/alerts/alert-form.tsx | D70: YES | E70: YES
A71: 67 | B71: Part 11 | C71: components/alerts/alert-list.tsx | D71: YES | E71: YES
... A74: 70 | B74: Part 12 | C74: components/billing/subscription-card.tsx | D74: YES | E74: YES
A75: 71 | B75: Part 12 | C75: components/billing/invoice-list.tsx | E75: YES
A76: 72 | B76: Part 12 | C76: components/pricing/tier-comparison.tsx | E76: YES
A77: 73 | B77: Part 14 | C77: components/admin/FraudAlertCard.tsx | D77: YES | E77: YES
A78: 74 | B78: Part 14 | C78: components/admin/FraudPatternBadge.tsx | E78: YES
A79: 75 | B79: Part 14 | C79: components/admin/affiliate-filters.tsx | D79: YES | E79: YES
A80: 76 | B80: Part 14 | C80: components/admin/affiliate-stats-banner.tsx | E80: YES
A81: 77 | B81: Part 14 | C81: components/admin/affiliate-table.tsx | D81: YES | E81: YES
A82: 78 | B82: Part 14 | C82: components/admin/code-inventory-chart.tsx | E82: YES
A83: 79 | B83: Part 14 | C83: components/admin/commission-owings-table.tsx | D83: YES | E83: YES
A84: 80 | B84: Part 14 | C84: components/admin/distribute-codes-modal.tsx | D84: YES | E84: YES
A85: 81 | B85: Part 14 | C85: components/admin/pay-commission-modal.tsx | D85: YES | E85: YES
A86: 82 | B86: Part 14 | C86: components/admin/pnl-breakdown-table.tsx | E86: YES
A87: 83 | B87: Part 14 | C87: components/admin/pnl-summary-cards.tsx | E87: YES
A88: 84 | B88: Part 14 | C88: components/admin/pnl-trend-chart.tsx | E88: YES
A89: 85 | B89: Part 14 | C89: components/admin/sales-performance-table.tsx | E89: YES
A90: 86 | B90: Part 14 | C90: components/admin/suspend-affiliate-modal.tsx | D90: YES | E90: YES
A91: 87 | B91: Part 15 | C91: components/notifications/notification-bell.tsx | D91: YES | E91: YES
A92: 88 | B92: Part 15 | C92: components/notifications/notification-list.tsx | D92: YES | E92: YES
A93: 89 | B93: Part 16 | C93: app/layout.tsx | E93: YES
A94: 90 | B94: Part 16 | C94: app/(marketing)/layout.tsx | E94: YES
A95: 91 | B95: Part 16 | C95: app/(marketing)/page.tsx | D95: YES | E95: YES
A96: 92 | B96: Part 17A-2 | C96: components/affiliate/stats-card.tsx | E96: YES
A97: 93 | B97: Part 17A-2 | C97: components/affiliate/code-table.tsx | D97: YES | E97: YES
A98: 94 | B98: Part 17A-2 | C98: components/affiliate/commission-table.tsx | E98: YES
A99: 95 | B99: Part 17A-2 | C99: app/affiliate/register/page.tsx | D99: YES | E99: YES
A100: 96 | B100: Part 17A-2 | C100: app/affiliate/verify/page.tsx | D100: YES | E100: YES
A101: 97 | B101: Part 17A-2 | C101: app/affiliate/dashboard/page.tsx | D101: YES | E101: YES
A102: 98 | B102: Part 17A-2 | C102: app/affiliate/dashboard/codes/page.tsx | D102: YES | E102: YES
A103: 99 | B103: Part 17A-2 | C103: app/affiliate/dashboard/commissions/page.tsx | D103: YES | E103: YES
A104: 100 | B104: Part 17A-2 | C104: app/affiliate/dashboard/profile/page.tsx | D104: YES | E104: YES
A105: 101 | B105: Part 17A-2 | C105: app/affiliate/dashboard/profile/payment/page.tsx | D105: YES | E105: YES
A106: 102 | B106: Part 17B-1 | C106: app/admin/affiliates/page.tsx | D106: YES | E106: YES
A107: 103 | B107: Part 17B-1 | C107: app/admin/affiliates/[id]/page.tsx | D107: YES | E107: YES
A108: 104 | B108: Part 17B-1 | C108: app/admin/affiliates/reports/profit-loss/page.tsx | D108: YES | E108: YES
A109: 105 | B109: Part 17B-1 | C109: app/admin/affiliates/reports/sales-performance/page.tsx | D109: YES | E109: YES
A110: 106 | B110: Part 17B-1 | C110: app/admin/affiliates/reports/commission-owings/page.tsx | D110: YES | E110: YES
... A115: 111 | B115: Part 18C | C115: components/payments/PaymentMethodSelector.tsx | D115: YES | E115: YES
...

Sheet Sheet6
B2: app/(auth)/forgot-password/page.tsx
B3: app/(auth)/layout.tsx
B4: app/(auth)/login/page.tsx
B5: app/(auth)/register/page.tsx
B6: app/(auth)/reset-password/page.tsx
B7: app/(auth)/verify-email/page.tsx
B8: app/(auth)/verify-email/pending/page.tsx
B9: app/(dashboard)/admin/api-usage/page.tsx
B10: app/(dashboard)/admin/disbursement/accounts/page.tsx
B11: app/(dashboard)/admin/disbursement/affiliates/page.tsx
B12: app/(dashboard)/admin/disbursement/audit/page.tsx
B13: app/(dashboard)/admin/disbursement/batches/[batchId]/page.tsx
... B125: components/watchlist/watchlist-item.tsx

Sheet Frontend files Collation
A1: app/(admin)/admin/affiliates/[id]/loading.tsx | B1: =RIGHT(A1, 4)=".tsx" -> TRUE
A2: app/(admin)/admin/affiliates/[id]/page.tsx | B2: =RIGHT(A2, 4)=".tsx" -> TRUE
A3: app/(admin)/admin/affiliates/loading.tsx | B3: =RIGHT(A3, 4)=".tsx" -> TRUE
A4: app/(admin)/admin/affiliates/page.tsx | B4: =RIGHT(A4, 4)=".tsx" -> TRUE
A5: app/(admin)/admin/affiliates/reports/code-inventory/page.tsx | B5: =RIGHT(A5, 4)=".tsx" -> TRUE
A6: app/(admin)/admin/affiliates/reports/commission-owings/page.tsx | B6: =RIGHT(A6, 4)=".tsx" -> TRUE
A7: app/(admin)/admin/affiliates/reports/profit-loss/page.tsx | B7: =RIGHT(A7, 4)=".tsx" -> TRUE
A8: app/(admin)/admin/affiliates/reports/sales-performance/page.tsx | B8: =RIGHT(A8, 4)=".tsx" -> TRUE
A9: app/(admin)/admin/analytics/loading.tsx | B9: =RIGHT(A9, 4)=".tsx" -> TRUE
A10: app/(admin)/admin/analytics/page.tsx | B10: =RIGHT(A10, 4)=".tsx" -> TRUE
A11: app/(admin)/admin/api-usage/loading.tsx | B11: =RIGHT(A11, 4)=".tsx" -> TRUE
A12: app/(admin)/admin/api-usage/page.tsx | B12: =RIGHT(A12, 4)=".tsx" -> TRUE
... A296: components/watchlist/watchlist-panel.tsx | B296: =RIGHT(A296, 4)=".tsx" -> TRUE

Sheet Exist in frontend but not root
A1: Frontend files exist in frontend/* but not in root
B3: app/(admin)/admin/affiliates/[id]/loading.tsx | D3: 1 | E3: ="frontend/" & B3 -> frontend/app/(admin)/admin/affiliates/[id]/loading.tsx
B4: app/(admin)/admin/affiliates/[id]/page.tsx | D4: =D3+1 -> 2 | E4: ="frontend/" & B4 -> frontend/app/(admin)/admin/affiliates/[id]/page.tsx
B5: app/(admin)/admin/affiliates/loading.tsx | D5: =D4+1 -> 3 | E5: ="frontend/" & B5 -> frontend/app/(admin)/admin/affiliates/loading.tsx
B6: app/(admin)/admin/affiliates/page.tsx | D6: =D5+1 -> 4 | E6: ="frontend/" & B6 -> frontend/app/(admin)/admin/affiliates/page.tsx
B7: app/(admin)/admin/affiliates/reports/code-inventory/page.tsx | D7: =D6+1 -> 5 | E7: ="frontend/" & B7 -> frontend/app/(admin)/admin/affiliates/reports/code-inventory/page.tsx
B8: app/(admin)/admin/affiliates/reports/commission-owings/page.tsx | D8: =D7+1 -> 6 | E8: ="frontend/" & B8 -> frontend/app/(admin)/admin/affiliates/reports/commission-owings/page.tsx
B9: app/(admin)/admin/affiliates/reports/profit-loss/page.tsx | D9: =D8+1 -> 7 | E9: ="frontend/" & B9 -> frontend/app/(admin)/admin/affiliates/reports/profit-loss/page.tsx
B10: app/(admin)/admin/affiliates/reports/sales-performance/page.tsx | D10: =D9+1 -> 8 | E10: ="frontend/" & B10 -> frontend/app/(admin)/admin/affiliates/reports/sales-performance/page.tsx
B11: app/(admin)/admin/analytics/loading.tsx | D11: =D10+1 -> 9 | E11: ="frontend/" & B11 -> frontend/app/(admin)/admin/analytics/loading.tsx
B12: app/(admin)/admin/analytics/page.tsx | D12: =D11+1 -> 10 | E12: ="frontend/" & B12 -> frontend/app/(admin)/admin/analytics/page.tsx
B13: app/(admin)/admin/api-usage/loading.tsx | D13: =D12+1 -> 11 | E13: ="frontend/" & B13 -> frontend/app/(admin)/admin/api-usage/loading.tsx
B14: app/(admin)/admin/api-usage/page.tsx | D14: =D13+1 -> 12 | E14: ="frontend/" & B14 -> frontend/app/(admin)/admin/api-usage/page.tsx
B15: app/(admin)/admin/error-logs/page.tsx | D15: =D14+1 -> 13 | E15: ="frontend/" & B15 -> frontend/app/(admin)/admin/error-logs/page.tsx
... B144: components/watchlist/watchlist-panel.tsx | D144: =D143+1 -> 142 | E144: ="frontend/" & B144 -> frontend/components/watchlist/watchlist-panel.tsx

Sheet Exist in root but not frontend
A1: Frontend files exist in root but not in frontend/*
A3: 1 | B3: app/(dashboard)/admin/api-usage/page.tsx
A4: =A3+1 -> 2 | B4: app/(dashboard)/admin/disbursement/accounts/page.tsx
A5: =A4+1 -> 3 | B5: app/(dashboard)/admin/disbursement/affiliates/page.tsx
A6: =A5+1 -> 4 | B6: app/(dashboard)/admin/disbursement/audit/page.tsx
A7: =A6+1 -> 5 | B7: app/(dashboard)/admin/disbursement/batches/[batchId]/page.tsx
A8: =A7+1 -> 6 | B8: app/(dashboard)/admin/disbursement/batches/page.tsx
A9: =A8+1 -> 7 | B9: app/(dashboard)/admin/disbursement/config/page.tsx
A10: =A9+1 -> 8 | B10: app/(dashboard)/admin/disbursement/layout.tsx
A11: =A10+1 -> 9 | B11: app/(dashboard)/admin/disbursement/page.tsx
A12: =A11+1 -> 10 | B12: app/(dashboard)/admin/disbursement/transactions/page.tsx
A13: =A12+1 -> 11 | B13: app/(dashboard)/admin/disbursements/[id]/page.tsx
A14: =A13+1 -> 12 | B14: app/(dashboard)/admin/disbursements/accounts/page.tsx
A15: =A14+1 -> 13 | B15: app/(dashboard)/admin/disbursements/affiliates/page.tsx
... A99: =A98+1 -> 97 | B99: components/watchlist/timeframe-grid.tsx

Sheet Frontend TSX
F1: 1 | G1: frontend/app/(auth)/forgot-password/page.tsx | H1: 1 | I1: =REPLACE(G1, 1, 10, "") -> app/(auth)/forgot-password/page.tsx
F2: 2 | G2: frontend/app/(auth)/layout.tsx | H2: =H1+1 -> 2 | I2: =REPLACE(G2, 1, 10, "") -> app/(auth)/layout.tsx
F3: 3 | G3: frontend/app/(auth)/loading.tsx | H3: =H2+1 -> 3 | I3: =REPLACE(G3, 1, 10, "") -> app/(auth)/loading.tsx
F4: 4 | G4: frontend/app/(auth)/login/page.tsx | H4: =H3+1 -> 4 | I4: =REPLACE(G4, 1, 10, "") -> app/(auth)/login/page.tsx
F5: 5 | G5: frontend/app/(auth)/register/page.tsx | H5: =H4+1 -> 5 | I5: =REPLACE(G5, 1, 10, "") -> app/(auth)/register/page.tsx
F6: 6 | G6: frontend/app/(auth)/reset-password/page.tsx | H6: =H5+1 -> 6 | I6: =REPLACE(G6, 1, 10, "") -> app/(auth)/reset-password/page.tsx
F7: 7 | G7: frontend/app/(auth)/verify-2fa/page.tsx | H7: =H6+1 -> 7 | I7: =REPLACE(G7, 1, 10, "") -> app/(auth)/verify-2fa/page.tsx
F8: 8 | G8: frontend/app/(auth)/verify-email/page.tsx | H8: =H7+1 -> 8 | I8: =REPLACE(G8, 1, 10, "") -> app/(auth)/verify-email/page.tsx
F9: 9 | G9: frontend/app/(auth)/verify-email/pending/page.tsx | H9: =H8+1 -> 9 | I9: =REPLACE(G9, 1, 10, "") -> app/(auth)/verify-email/pending/page.tsx
F10: 10 | G10: frontend/app/(dashboard)/admin/api-usage/page.tsx | H10: =H9+1 -> 10 | I10: =REPLACE(G10, 1, 10, "") -> app/(dashboard)/admin/api-usage/page.tsx
F11: 11 | G11: frontend/app/(dashboard)/admin/disbursement/accounts/page.tsx | H11: =H10+1 -> 11 | I11: =REPLACE(G11, 1, 10, "") -> app/(dashboard)/admin/disbursement/accounts/page.tsx
F12: 12 | G12: frontend/app/(dashboard)/admin/disbursement/affiliates/page.tsx | H12: =H11+1 -> 12 | I12: =REPLACE(G12, 1, 10, "") -> app/(dashboard)/admin/disbursement/affiliates/page.tsx
F13: 13 | G13: frontend/app/(dashboard)/admin/disbursement/audit/page.tsx | H13: =H12+1 -> 13 | I13: =REPLACE(G13, 1, 10, "") -> app/(dashboard)/admin/disbursement/audit/page.tsx
... F162: 162 | G162: frontend/lib/email/templates/affiliate/welcome.tsx | H162: =H161+1 -> 162 | I162: =REPLACE(G162, 1, 10, "") -> lib/email/templates/affiliate/welcome.tsx

Sheet Monolith TSX
C1: 1 | D1: `app/(auth)/forgot-password/page.tsx` | K1: 1 | L1: =TRIM(SUBSTITUTE(SUBSTITUTE(D1, LEFT(D1, FIND("app/", D1)-1), ""), "`", "")) -> app/(auth)/forgot-password/page.tsx
C2: 2 | D2: `app/(auth)/layout.tsx` | K2: =K1+1 -> 2 | L2: =TRIM(SUBSTITUTE(SUBSTITUTE(D2, LEFT(D2, FIND("app/", D2)-1), ""), "`", "")) -> app/(auth)/layout.tsx
C3: 3 | D3: `app/(auth)/login/page.tsx` | K3: =K2+1 -> 3 | L3: =TRIM(SUBSTITUTE(SUBSTITUTE(D3, LEFT(D3, FIND("app/", D3)-1), ""), "`", "")) -> app/(auth)/login/page.tsx
C4: 4 | D4: `app/(auth)/register/page.tsx` | K4: =K3+1 -> 4 | L4: =TRIM(SUBSTITUTE(SUBSTITUTE(D4, LEFT(D4, FIND("app/", D4)-1), ""), "`", "")) -> app/(auth)/register/page.tsx
C5: 5 | D5: `app/(auth)/reset-password/page.tsx` | K5: =K4+1 -> 5 | L5: =TRIM(SUBSTITUTE(SUBSTITUTE(D5, LEFT(D5, FIND("app/", D5)-1), ""), "`", "")) -> app/(auth)/reset-password/page.tsx
C6: 6 | D6: `app/(auth)/verify-2fa/page.tsx` | K6: =K5+1 -> 6 | L6: =TRIM(SUBSTITUTE(SUBSTITUTE(D6, LEFT(D6, FIND("app/", D6)-1), ""), "`", "")) -> app/(auth)/verify-2fa/page.tsx
C7: 7 | D7: `app/(auth)/verify-email/page.tsx` | K7: =K6+1 -> 7 | L7: =TRIM(SUBSTITUTE(SUBSTITUTE(D7, LEFT(D7, FIND("app/", D7)-1), ""), "`", "")) -> app/(auth)/verify-email/page.tsx
C8: 8 | D8: `app/(auth)/verify-email/pending/page.tsx` | K8: =K7+1 -> 8 | L8: =TRIM(SUBSTITUTE(SUBSTITUTE(D8, LEFT(D8, FIND("app/", D8)-1), ""), "`", "")) -> app/(auth)/verify-email/pending/page.tsx
C9: 9 | D9: `app/(dashboard)/admin/api-usage/page.tsx` | K9: =K8+1 -> 9 | L9: =TRIM(SUBSTITUTE(SUBSTITUTE(D9, LEFT(D9, FIND("app/", D9)-1), ""), "`", "")) -> app/(dashboard)/admin/api-usage/page.tsx
C10: 10 | D10: `app/(dashboard)/admin/disbursement/accounts/page.tsx` | K10: =K9+1 -> 10 | L10: =TRIM(SUBSTITUTE(SUBSTITUTE(D10, LEFT(D10, FIND("app/", D10)-1), ""), "`", "")) -> app/(dashboard)/admin/disbursement/accounts/page.tsx
C11: 11 | D11: `app/(dashboard)/admin/disbursement/affiliates/page.tsx` | K11: =K10+1 -> 11 | L11: =TRIM(SUBSTITUTE(SUBSTITUTE(D11, LEFT(D11, FIND("app/", D11)-1), ""), "`", "")) -> app/(dashboard)/admin/disbursement/affiliates/page.tsx
C12: 12 | D12: `app/(dashboard)/admin/disbursement/audit/page.tsx` | K12: =K11+1 -> 12 | L12: =TRIM(SUBSTITUTE(SUBSTITUTE(D12, LEFT(D12, FIND("app/", D12)-1), ""), "`", "")) -> app/(dashboard)/admin/disbursement/audit/page.tsx
C13: 13 | D13: `app/(dashboard)/admin/disbursement/batches/[batchId]/page.tsx` | K13: =K12+1 -> 13 | L13: =TRIM(SUBSTITUTE(SUBSTITUTE(D13, LEFT(D13, FIND("app/", D13)-1), ""), "`", "")) -> app/(dashboard)/admin/disbursement/batches/[batchId]/page.tsx
... C74: 74 | D74: `app/test-api/page.tsx` | K74: =K73+1 -> 74 | L74: =TRIM(SUBSTITUTE(SUBSTITUTE(D74, LEFT(D74, FIND("app/", D74)-1), ""), "`", "")) -> app/test-api/page.tsx
C75: 1 | D75: `components/admin/FraudAlertCard.tsx` | K75: =K74+1 -> 75 | L75: =TRIM(SUBSTITUTE(SUBSTITUTE(D75, LEFT(D75, FIND("components/", D75)-1), ""), "`", "")) -> components/admin/FraudAlertCard.tsx
C76: 2 | D76: `components/admin/FraudPatternBadge.tsx` | K76: =K75+1 -> 76 | L76: =TRIM(SUBSTITUTE(SUBSTITUTE(D76, LEFT(D76, FIND("components/", D76)-1), ""), "`", "")) -> components/admin/FraudPatternBadge.tsx
C77: 3 | D77: `components/admin/affiliate-filters.tsx` | K77: =K76+1 -> 77 | L77: =TRIM(SUBSTITUTE(SUBSTITUTE(D77, LEFT(D77, FIND("components/", D77)-1), ""), "`", "")) -> components/admin/affiliate-filters.tsx
C78: 4 | D78: `components/admin/affiliate-stats-banner.tsx` | K78: =K77+1 -> 78 | L78: =TRIM(SUBSTITUTE(SUBSTITUTE(D78, LEFT(D78, FIND("components/", D78)-1), ""), "`", "")) -> components/admin/affiliate-stats-banner.tsx
C79: 5 | D79: `components/admin/affiliate-table.tsx` | K79: =K78+1 -> 79 | L79: =TRIM(SUBSTITUTE(SUBSTITUTE(D79, LEFT(D79, FIND("components/", D79)-1), ""), "`", "")) -> components/admin/affiliate-table.tsx
C80: 6 | D80: `components/admin/code-inventory-chart.tsx` | K80: =K79+1 -> 80 | L80: =TRIM(SUBSTITUTE(SUBSTITUTE(D80, LEFT(D80, FIND("components/", D80)-1), ""), "`", "")) -> components/admin/code-inventory-chart.tsx
C81: 7 | D81: `components/admin/commission-owings-table.tsx` | K81: =K80+1 -> 81 | L81: =TRIM(SUBSTITUTE(SUBSTITUTE(D81, LEFT(D81, FIND("components/", D81)-1), ""), "`", "")) -> components/admin/commission-owings-table.tsx
C82: 8 | D82: `components/admin/distribute-codes-modal.tsx` | K82: =K81+1 -> 82 | L82: =TRIM(SUBSTITUTE(SUBSTITUTE(D82, LEFT(D82, FIND("components/", D82)-1), ""), "`", "")) -> components/admin/distribute-codes-modal.tsx
C83: 9 | D83: `components/admin/pay-commission-modal.tsx` | K83: =K82+1 -> 83 | L83: =TRIM(SUBSTITUTE(SUBSTITUTE(D83, LEFT(D83, FIND("components/", D83)-1), ""), "`", "")) -> components/admin/pay-commission-modal.tsx
C84: 10 | D84: `components/admin/pnl-breakdown-table.tsx` | K84: =K83+1 -> 84 | L84: =TRIM(SUBSTITUTE(SUBSTITUTE(D84, LEFT(D84, FIND("components/", D84)-1), ""), "`", "")) -> components/admin/pnl-breakdown-table.tsx
C85: 11 | D85: `components/admin/pnl-summary-cards.tsx` | K85: =K84+1 -> 85 | L85: =TRIM(SUBSTITUTE(SUBSTITUTE(D85, LEFT(D85, FIND("components/", D85)-1), ""), "`", "")) -> components/admin/pnl-summary-cards.tsx
C86: 12 | D86: `components/admin/pnl-trend-chart.tsx` | K86: =K85+1 -> 86 | L86: =TRIM(SUBSTITUTE(SUBSTITUTE(D86, LEFT(D86, FIND("components/", D86)-1), ""), "`", "")) -> components/admin/pnl-trend-chart.tsx
... C151: 77 | D151: `components/theme-toggle.tsx` | K151: =K150+1 -> 151 | L151: =TRIM(SUBSTITUTE(SUBSTITUTE(D151, LEFT(D151, FIND("components/", D151)-1), ""), "`", "")) -> components/theme-toggle.tsx
C152: 1 | D152: `lib/email/templates/affiliate/code-distributed.tsx` | K152: =K151+1 -> 152 | L152: =TRIM(SUBSTITUTE(SUBSTITUTE(D152, LEFT(D152, FIND("lib/", D152)-1), ""), "`", "")) -> lib/email/templates/affiliate/code-distributed.tsx
C153: 2 | D153: `lib/email/templates/affiliate/code-used.tsx` | K153: =K152+1 -> 153 | L153: =TRIM(SUBSTITUTE(SUBSTITUTE(D153, LEFT(D153, FIND("lib/", D153)-1), ""), "`", "")) -> lib/email/templates/affiliate/code-used.tsx
C154: 3 | D154: `lib/email/templates/affiliate/monthly-report.tsx` | K154: =K153+1 -> 154 | L154: =TRIM(SUBSTITUTE(SUBSTITUTE(D154, LEFT(D154, FIND("lib/", D154)-1), ""), "`", "")) -> lib/email/templates/affiliate/monthly-report.tsx
C155: 4 | D155: `lib/email/templates/affiliate/payment-processed.tsx` | K155: =K154+1 -> 155 | L155: =TRIM(SUBSTITUTE(SUBSTITUTE(D155, LEFT(D155, FIND("lib/", D155)-1), ""), "`", "")) -> lib/email/templates/affiliate/payment-processed.tsx
C156: 5 | D156: `lib/email/templates/affiliate/welcome.tsx` | K156: =K155+1 -> 156 | L156: =TRIM(SUBSTITUTE(SUBSTITUTE(D156, LEFT(D156, FIND("lib/", D156)-1), ""), "`", "")) -> lib/email/templates/affiliate/welcome.tsx
C157: 1 | D157: `emails/payment-confirmation.tsx` | K157: =K156+1 -> 157 | L157: =TRIM(SUBSTITUTE(SUBSTITUTE(D157, LEFT(D157, FIND("emails/", D157)-1), ""), "`", "")) -> emails/payment-confirmation.tsx
C158: 2 | D158: `emails/payment-failure.tsx` | K158: =K157+1 -> 158 | L158: =TRIM(SUBSTITUTE(SUBSTITUTE(D158, LEFT(D158, FIND("emails/", D158)-1), ""), "`", "")) -> emails/payment-failure.tsx
C159: 3 | D159: `emails/renewal-reminder.tsx` | K159: =K158+1 -> 159 | L159: =TRIM(SUBSTITUTE(SUBSTITUTE(D159, LEFT(D159, FIND("emails/", D159)-1), ""), "`", "")) -> emails/renewal-reminder.tsx
C160: 4 | D160: `emails/subscription-expired.tsx` | K160: =K159+1 -> 160 | L160: =TRIM(SUBSTITUTE(SUBSTITUTE(D160, LEFT(D160, FIND("emails/", D160)-1), ""), "`", "")) -> emails/subscription-expired.tsx
C161: 1 | D161: `__tests__/components/admin/affiliate-filters.test.tsx` | K161: =K160+1 -> 161 | L161: =TRIM(SUBSTITUTE(SUBSTITUTE(D161, LEFT(D161, FIND("__tests__/", D161)-1), ""), "`", "")) -> __tests__/components/admin/affiliate-filters.test.tsx
C162: 2 | D162: `__tests__/components/admin/affiliate-stats-banner.test.tsx` | K162: =K161+1 -> 162 | L162: =TRIM(SUBSTITUTE(SUBSTITUTE(D162, LEFT(D162, FIND("__tests__/", D162)-1), ""), "`", "")) -> __tests__/components/admin/affiliate-stats-banner.test.tsx
C163: 3 | D163: `__tests__/components/admin/code-inventory-chart.test.tsx` | K163: =K162+1 -> 163 | L163: =TRIM(SUBSTITUTE(SUBSTITUTE(D163, LEFT(D163, FIND("__tests__/", D163)-1), ""), "`", "")) -> __tests__/components/admin/code-inventory-chart.test.tsx
C164: 4 | D164: `__tests__/components/admin/fraud-alert-card.test.tsx` | K164: =K163+1 -> 164 | L164: =TRIM(SUBSTITUTE(SUBSTITUTE(D164, LEFT(D164, FIND("__tests__/", D164)-1), ""), "`", "")) -> __tests__/components/admin/fraud-alert-card.test.tsx
C165: 5 | D165: `__tests__/components/admin/fraud-pattern-badge.test.tsx` | K165: =K164+1 -> 165 | L165: =TRIM(SUBSTITUTE(SUBSTITUTE(D165, LEFT(D165, FIND("__tests__/", D165)-1), ""), "`", "")) -> __tests__/components/admin/fraud-pattern-badge.test.tsx
C166: 6 | D166: `__tests__/components/admin/pnl-breakdown-table.test.tsx` | K166: =K165+1 -> 166 | L166: =TRIM(SUBSTITUTE(SUBSTITUTE(D166, LEFT(D166, FIND("__tests__/", D166)-1), ""), "`", "")) -> __tests__/components/admin/pnl-breakdown-table.test.tsx
C167: 7 | D167: `__tests__/components/admin/pnl-summary-cards.test.tsx` | K167: =K166+1 -> 167 | L167: =TRIM(SUBSTITUTE(SUBSTITUTE(D167, LEFT(D167, FIND("__tests__/", D167)-1), ""), "`", "")) -> __tests__/components/admin/pnl-summary-cards.test.tsx
C168: 8 | D168: `__tests__/components/admin/sales-performance-table.test.tsx` | K168: =K167+1 -> 168 | L168: =TRIM(SUBSTITUTE(SUBSTITUTE(D168, LEFT(D168, FIND("__tests__/", D168)-1), ""), "`", "")) -> __tests__/components/admin/sales-performance-table.test.tsx
C169: 9 | D169: `__tests__/components/affiliate/code-table.test.tsx` | K169: =K168+1 -> 169 | L169: =TRIM(SUBSTITUTE(SUBSTITUTE(D169, LEFT(D169, FIND("__tests__/", D169)-1), ""), "`", "")) -> __tests__/components/affiliate/code-table.test.tsx
C170: 10 | D170: `__tests__/components/affiliate/commission-table.test.tsx` | K170: =K169+1 -> 170 | L170: =TRIM(SUBSTITUTE(SUBSTITUTE(D170, LEFT(D170, FIND("__tests__/", D170)-1), ""), "`", "")) -> __tests__/components/affiliate/commission-table.test.tsx
C171: 11 | D171: `__tests__/components/affiliate/stats-card.test.tsx` | K171: =K170+1 -> 171 | L171: =TRIM(SUBSTITUTE(SUBSTITUTE(D171, LEFT(D171, FIND("__tests__/", D171)-1), ""), "`", "")) -> __tests__/components/affiliate/stats-card.test.tsx
C172: 12 | D172: `__tests__/components/charts/indicator-toggles.test.tsx` | K172: =K171+1 -> 172 | L172: =TRIM(SUBSTITUTE(SUBSTITUTE(D172, LEFT(D172, FIND("__tests__/", D172)-1), ""), "`", "")) -> __tests__/components/charts/indicator-toggles.test.tsx
... C182: 22 | D182: `__tests__/components/ui/card.test.tsx` | K182: =K181+1 -> 182 | L182: =TRIM(SUBSTITUTE(SUBSTITUTE(D182, LEFT(D182, FIND("__tests__/", D182)-1), ""), "`", "")) -> __tests__/components/ui/card.test.tsx

Sheet Frontend-Monolith TSX
C1: FRONTEND | F1: MONOLITH | H1: Matched
B2: 1 | E2: 1 | F2: __tests__/components/admin/affiliate-filters.test.tsx | H2: =C2=F2 -> FALSE
B3: =B2+1 -> 2 | E3: =E2+1 -> 2 | F3: __tests__/components/admin/affiliate-stats-banner.test.tsx | H3: =C3=F3 -> FALSE
B4: =B3+1 -> 3 | E4: =E3+1 -> 3 | F4: __tests__/components/admin/code-inventory-chart.test.tsx | H4: =C4=F4 -> FALSE
B5: =B4+1 -> 4 | E5: =E4+1 -> 4 | F5: __tests__/components/admin/fraud-alert-card.test.tsx | H5: =C5=F5 -> FALSE
B6: =B5+1 -> 5 | E6: =E5+1 -> 5 | F6: __tests__/components/admin/fraud-pattern-badge.test.tsx | H6: =C6=F6 -> FALSE
B7: =B6+1 -> 6 | E7: =E6+1 -> 6 | F7: __tests__/components/admin/pnl-breakdown-table.test.tsx | H7: =C7=F7 -> FALSE
B8: =B7+1 -> 7 | E8: =E7+1 -> 7 | F8: __tests__/components/admin/pnl-summary-cards.test.tsx | H8: =C8=F8 -> FALSE
B9: =B8+1 -> 8 | E9: =E8+1 -> 8 | F9: __tests__/components/admin/sales-performance-table.test.tsx | H9: =C9=F9 -> FALSE
B10: =B9+1 -> 9 | E10: =E9+1 -> 9 | F10: __tests__/components/affiliate/code-table.test.tsx | H10: =C10=F10 -> FALSE
B11: =B10+1 -> 10 | E11: =E10+1 -> 10 | F11: __tests__/components/affiliate/commission-table.test.tsx | H11: =C11=F11 -> FALSE
B12: =B11+1 -> 11 | E12: =E11+1 -> 11 | F12: __tests__/components/affiliate/stats-card.test.tsx | H12: =C12=F12 -> FALSE
B13: =B12+1 -> 12 | E13: =E12+1 -> 12 | F13: __tests__/components/charts/indicator-toggles.test.tsx | H13: =C13=F13 -> FALSE
B14: =B13+1 -> 13 | E14: =E13+1 -> 13 | F14: __tests__/components/charts/pro-indicator-overlay.test.tsx | H14: =C14=F14 -> FALSE
... B23: =B22+1 -> 22 | E23: =E22+1 -> 22 | F23: __tests__/components/ui/card.test.tsx | H23: =C23=F23 -> FALSE
B24: =B23+1 -> 23 | C24: app/(auth)/forgot-password/page.tsx | E24: =E23+1 -> 23 | F24: app/(auth)/forgot-password/page.tsx | H24: =C24=F24 -> TRUE
B25: =B24+1 -> 24 | C25: app/(auth)/layout.tsx | E25: =E24+1 -> 24 | F25: app/(auth)/layout.tsx | H25: =C25=F25 -> TRUE
B26: =B25+1 -> 25 | C26: app/(auth)/loading.tsx | E26: =E25+1 -> 25 | H26: =C26=F26 -> FALSE
B27: =B26+1 -> 26 | C27: app/(auth)/login/page.tsx | E27: =E26+1 -> 26 | F27: app/(auth)/login/page.tsx | H27: =C27=F27 -> TRUE
B28: =B27+1 -> 27 | C28: app/(auth)/register/page.tsx | E28: =E27+1 -> 27 | F28: app/(auth)/register/page.tsx | H28: =C28=F28 -> TRUE
B29: =B28+1 -> 28 | C29: app/(auth)/reset-password/page.tsx | E29: =E28+1 -> 28 | F29: app/(auth)/reset-password/page.tsx | H29: =C29=F29 -> TRUE
B30: =B29+1 -> 29 | C30: app/(auth)/verify-2fa/page.tsx | E30: =E29+1 -> 29 | F30: app/(auth)/verify-2fa/page.tsx | H30: =C30=F30 -> TRUE
B31: =B30+1 -> 30 | C31: app/(auth)/verify-email/page.tsx | E31: =E30+1 -> 30 | F31: app/(auth)/verify-email/page.tsx | H31: =C31=F31 -> TRUE
B32: =B31+1 -> 31 | C32: app/(auth)/verify-email/pending/page.tsx | E32: =E31+1 -> 31 | F32: app/(auth)/verify-email/pending/page.tsx | H32: =C32=F32 -> TRUE
B33: =B32+1 -> 32 | C33: app/(dashboard)/admin/api-usage/page.tsx | E33: =E32+1 -> 32 | F33: app/(dashboard)/admin/api-usage/page.tsx | H33: =C33=F33 -> TRUE
B34: =B33+1 -> 33 | C34: app/(dashboard)/admin/disbursement/accounts/page.tsx | E34: =E33+1 -> 33 | F34: app/(dashboard)/admin/disbursement/accounts/page.tsx | H34: =C34=F34 -> TRUE
B35: =B34+1 -> 34 | C35: app/(dashboard)/admin/disbursement/affiliates/page.tsx | E35: =E34+1 -> 34 | F35: app/(dashboard)/admin/disbursement/affiliates/page.tsx | H35: =C35=F35 -> TRUE
B36: =B35+1 -> 35 | C36: app/(dashboard)/admin/disbursement/audit/page.tsx | E36: =E35+1 -> 35 | F36: app/(dashboard)/admin/disbursement/audit/page.tsx | H36: =C36=F36 -> TRUE
B37: =B36+1 -> 36 | C37: app/(dashboard)/admin/disbursement/batches/[batchId]/page.tsx | E37: =E36+1 -> 36 | F37: app/(dashboard)/admin/disbursement/batches/[batchId]/page.tsx | H37: =C37=F37 -> TRUE
B38: =B37+1 -> 37 | C38: app/(dashboard)/admin/disbursement/batches/page.tsx | E38: =E37+1 -> 37 | F38: app/(dashboard)/admin/disbursement/batches/page.tsx | H38: =C38=F38 -> TRUE
... B46: =B45+1 -> 45 | C46: app/(dashboard)/admin/layout.tsx | E46: =E45+1 -> 45 | F46: app/(dashboard)/admin/layout.tsx | H46: =C46=F46 -> TRUE
B47: =B46+1 -> 46 | C47: app/(dashboard)/admin/loading.tsx | E47: =E46+1 -> 46 | H47: =C47=F47 -> FALSE
B48: =B47+1 -> 47 | C48: app/(dashboard)/admin/page.tsx | E48: =E47+1 -> 47 | F48: app/(dashboard)/admin/page.tsx | H48: =C48=F48 -> TRUE
B49: =B48+1 -> 48 | C49: app/(dashboard)/admin/users/page.tsx | E49: =E48+1 -> 48 | F49: app/(dashboard)/admin/users/page.tsx | H49: =C49=F49 -> TRUE
B50: =B49+1 -> 49 | C50: app/(dashboard)/alerts/alerts-client.tsx | E50: =E49+1 -> 49 | F50: app/(dashboard)/alerts/alerts-client.tsx | H50: =C50=F50 -> TRUE
B51: =B50+1 -> 50 | C51: app/(dashboard)/alerts/loading.tsx | E51: =E50+1 -> 50 | H51: =C51=F51 -> FALSE
B52: =B51+1 -> 51 | C52: app/(dashboard)/alerts/new/create-alert-client.tsx | E52: =E51+1 -> 51 | F52: app/(dashboard)/alerts/new/create-alert-client.tsx | H52: =C52=F52 -> TRUE
B53: =B52+1 -> 52 | C53: app/(dashboard)/alerts/new/page.tsx | E53: =E52+1 -> 52 | F53: app/(dashboard)/alerts/new/page.tsx | H53: =C53=F53 -> TRUE
B54: =B53+1 -> 53 | C54: app/(dashboard)/alerts/page.tsx | E54: =E53+1 -> 53 | F54: app/(dashboard)/alerts/page.tsx | H54: =C54=F54 -> TRUE
B55: =B54+1 -> 54 | C55: app/(dashboard)/charts/[symbol]/[timeframe]/page.tsx | E55: =E54+1 -> 54 | F55: app/(dashboard)/charts/[symbol]/[timeframe]/page.tsx | H55: =C55=F55 -> TRUE
B56: =B55+1 -> 55 | C56: app/(dashboard)/charts/[symbol]/[timeframe]/trading-chart-client.tsx | E56: =E55+1 -> 55 | F56: app/(dashboard)/charts/[symbol]/[timeframe]/trading-chart-client.tsx | H56: =C56=F56 -> TRUE
B57: =B56+1 -> 56 | C57: app/(dashboard)/charts/loading.tsx | E57: =E56+1 -> 56 | H57: =C57=F57 -> FALSE
B58: =B57+1 -> 57 | C58: app/(dashboard)/charts/page.tsx | E58: =E57+1 -> 57 | F58: app/(dashboard)/charts/page.tsx | H58: =C58=F58 -> TRUE
B59: =B58+1 -> 58 | C59: app/(dashboard)/dashboard/loading.tsx | E59: =E58+1 -> 58 | H59: =C59=F59 -> FALSE
B60: =B59+1 -> 59 | C60: app/(dashboard)/dashboard/page.tsx | E60: =E59+1 -> 59 | F60: app/(dashboard)/dashboard/page.tsx | H60: =C60=F60 -> TRUE
B61: =B60+1 -> 60 | C61: app/(dashboard)/layout.tsx | E61: =E60+1 -> 60 | F61: app/(dashboard)/layout.tsx | H61: =C61=F61 -> TRUE
B62: =B61+1 -> 61 | C62: app/(dashboard)/settings/account/page.tsx | E62: =E61+1 -> 61 | F62: app/(dashboard)/settings/account/page.tsx | H62: =C62=F62 -> TRUE
B63: =B62+1 -> 62 | C63: app/(dashboard)/settings/appearance/page.tsx | E63: =E62+1 -> 62 | F63: app/(dashboard)/settings/appearance/page.tsx | H63: =C63=F63 -> TRUE
B64: =B63+1 -> 63 | C64: app/(dashboard)/settings/billing/page.tsx | E64: =E63+1 -> 63 | F64: app/(dashboard)/settings/billing/page.tsx | H64: =C64=F64 -> TRUE
B65: =B64+1 -> 64 | C65: app/(dashboard)/settings/help/page.tsx | E65: =E64+1 -> 64 | F65: app/(dashboard)/settings/help/page.tsx | H65: =C65=F65 -> TRUE
B66: =B65+1 -> 65 | C66: app/(dashboard)/settings/language/page.tsx | E66: =E65+1 -> 65 | F66: app/(dashboard)/settings/language/page.tsx | H66: =C66=F66 -> TRUE
B67: =B66+1 -> 66 | C67: app/(dashboard)/settings/layout.tsx | E67: =E66+1 -> 66 | F67: app/(dashboard)/settings/layout.tsx | H67: =C67=F67 -> TRUE
B68: =B67+1 -> 67 | C68: app/(dashboard)/settings/loading.tsx | E68: =E67+1 -> 67 | H68: =C68=F68 -> FALSE
B69: =B68+1 -> 68 | C69: app/(dashboard)/settings/page.tsx | E69: =E68+1 -> 68 | F69: app/(dashboard)/settings/page.tsx | H69: =C69=F69 -> TRUE
B70: =B69+1 -> 69 | C70: app/(dashboard)/settings/privacy/page.tsx | E70: =E69+1 -> 69 | F70: app/(dashboard)/settings/privacy/page.tsx | H70: =C70=F70 -> TRUE
B71: =B70+1 -> 70 | C71: app/(dashboard)/settings/profile/page.tsx | E71: =E70+1 -> 70 | F71: app/(dashboard)/settings/profile/page.tsx | H71: =C71=F71 -> TRUE
B72: =B71+1 -> 71 | C72: app/(dashboard)/settings/security/page.tsx | E72: =E71+1 -> 71 | F72: app/(dashboard)/settings/security/page.tsx | H72: =C72=F72 -> TRUE
B73: =B72+1 -> 72 | C73: app/(dashboard)/settings/terms/page.tsx | E73: =E72+1 -> 72 | F73: app/(dashboard)/settings/terms/page.tsx | H73: =C73=F73 -> TRUE
B74: =B73+1 -> 73 | C74: app/(dashboard)/watchlist/page.tsx | E74: =E73+1 -> 73 | F74: app/(dashboard)/watchlist/page.tsx | H74: =C74=F74 -> TRUE
B75: =B74+1 -> 74 | C75: app/(dashboard)/watchlist/watchlist-client.tsx | E75: =E74+1 -> 74 | F75: app/(dashboard)/watchlist/watchlist-client.tsx | H75: =C75=F75 -> TRUE
B76: =B75+1 -> 75 | C76: app/(marketing)/landing-content.tsx | E76: =E75+1 -> 75 | F76: app/(marketing)/landing-content.tsx | H76: =C76=F76 -> TRUE
B77: =B76+1 -> 76 | C77: app/(marketing)/layout.tsx | E77: =E76+1 -> 76 | F77: app/(marketing)/layout.tsx | H77: =C77=F77 -> TRUE
B78: =B77+1 -> 77 | C78: app/(marketing)/page.tsx | E78: =E77+1 -> 77 | F78: app/(marketing)/page.tsx | H78: =C78=F78 -> TRUE
B79: =B78+1 -> 78 | C79: app/(marketing)/pricing/page.tsx | E79: =E78+1 -> 78 | F79: app/(marketing)/pricing/page.tsx | H79: =C79=F79 -> TRUE
B80: =B79+1 -> 79 | C80: app/admin/affiliates/[id]/page.tsx | E80: =E79+1 -> 79 | F80: app/admin/affiliates/[id]/page.tsx | H80: =C80=F80 -> TRUE
... B98: =B97+1 -> 97 | C98: app/affiliate/verify/page.tsx | E98: =E97+1 -> 97 | F98: app/affiliate/verify/page.tsx | H98: =C98=F98 -> TRUE
B99: =B98+1 -> 98 | C99: app/api-test/page.tsx | E99: =E98+1 -> 98 | H99: =C99=F99 -> FALSE
B100: =B99+1 -> 99 | C100: app/checkout/page.tsx | E100: =E99+1 -> 99 | F100: app/checkout/page.tsx | H100: =C100=F100 -> TRUE
B101: =B100+1 -> 100 | C101: app/error.tsx | E101: =E100+1 -> 100 | F101: app/error.tsx | H101: =C101=F101 -> TRUE
B102: =B101+1 -> 101 | C102: app/layout.tsx | E102: =E101+1 -> 101 | F102: app/layout.tsx | H102: =C102=F102 -> TRUE
B103: =B102+1 -> 102 | C103: app/providers.tsx | E103: =E102+1 -> 102 | F103: app/providers.tsx | H103: =C103=F103 -> TRUE
B104: =B103+1 -> 103 | E104: =E103+1 -> 103 | F104: app/test-api/page.tsx | H104: =C104=F104 -> FALSE
B105: =B104+1 -> 104 | C105: components/admin/affiliate-filters.tsx | E105: =E104+1 -> 104 | F105: components/admin/affiliate-filters.tsx | H105: =C105=F105 -> TRUE
B106: =B105+1 -> 105 | C106: components/admin/affiliate-stats-banner.tsx | E106: =E105+1 -> 105 | F106: components/admin/affiliate-stats-banner.tsx | H106: =C106=F106 -> TRUE
B107: =B106+1 -> 106 | C107: components/admin/affiliate-table.tsx | E107: =E106+1 -> 106 | F107: components/admin/affiliate-table.tsx | H107: =C107=F107 -> TRUE
B108: =B107+1 -> 107 | C108: components/admin/code-inventory-chart.tsx | E108: =E107+1 -> 107 | F108: components/admin/code-inventory-chart.tsx | H108: =C108=F108 -> TRUE
B109: =B108+1 -> 108 | C109: components/admin/commission-owings-table.tsx | E109: =E108+1 -> 108 | F109: components/admin/commission-owings-table.tsx | H109: =C109=F109 -> TRUE
B110: =B109+1 -> 109 | C110: components/admin/distribute-codes-modal.tsx | E110: =E109+1 -> 109 | F110: components/admin/distribute-codes-modal.tsx | H110: =C110=F110 -> TRUE
B111: =B110+1 -> 110 | C111: components/admin/FraudAlertCard.tsx | E111: =E110+1 -> 110 | F111: components/admin/FraudAlertCard.tsx | H111: =C111=F111 -> TRUE
B112: =B111+1 -> 111 | C112: components/admin/FraudPatternBadge.tsx | E112: =E111+1 -> 111 | F112: components/admin/FraudPatternBadge.tsx | H112: =C112=F112 -> TRUE
B113: =B112+1 -> 112 | C113: components/admin/pay-commission-modal.tsx | E113: =E112+1 -> 112 | F113: components/admin/pay-commission-modal.tsx | H113: =C113=F113 -> TRUE
B114: =B113+1 -> 113 | C114: components/admin/pnl-breakdown-table.tsx | E114: =E113+1 -> 113 | F114: components/admin/pnl-breakdown-table.tsx | H114: =C114=F114 -> TRUE
B115: =B114+1 -> 114 | C115: components/admin/pnl-summary-cards.tsx | E115: =E114+1 -> 114 | F115: components/admin/pnl-summary-cards.tsx | H115: =C115=F115 -> TRUE
B116: =B115+1 -> 115 | C116: components/admin/pnl-trend-chart.tsx | E116: =E115+1 -> 115 | F116: components/admin/pnl-trend-chart.tsx | H116: =C116=F116 -> TRUE
... B181: =B180+1 -> 180 | C181: components/watchlist/watchlist-item.tsx | E181: =E180+1 -> 180 | F181: components/watchlist/watchlist-item.tsx | H181: =C181=F181 -> TRUE
B182: =B181+1 -> 181 | E182: =E181+1 -> 181 | F182: emails/payment-confirmation.tsx | H182: =C182=F182 -> FALSE
B183: =B182+1 -> 182 | E183: =E182+1 -> 182 | F183: emails/payment-failure.tsx | H183: =C183=F183 -> FALSE
B184: =B183+1 -> 183 | E184: =E183+1 -> 183 | F184: emails/renewal-reminder.tsx | H184: =C184=F184 -> FALSE
B185: =B184+1 -> 184 | E185: =E184+1 -> 184 | F185: emails/subscription-expired.tsx | H185: =C185=F185 -> FALSE
B186: =B185+1 -> 185 | C186: lib/email/templates/affiliate/code-distributed.tsx | E186: =E185+1 -> 185 | F186: lib/email/templates/affiliate/code-distributed.tsx | H186: =C186=F186 -> TRUE
B187: =B186+1 -> 186 | C187: lib/email/templates/affiliate/code-used.tsx | E187: =E186+1 -> 186 | F187: lib/email/templates/affiliate/code-used.tsx | H187: =C187=F187 -> TRUE
B188: =B187+1 -> 187 | C188: lib/email/templates/affiliate/monthly-report.tsx | E188: =E187+1 -> 187 | F188: lib/email/templates/affiliate/monthly-report.tsx | H188: =C188=F188 -> TRUE
B189: =B188+1 -> 188 | C189: lib/email/templates/affiliate/payment-processed.tsx | E189: =E188+1 -> 188 | F189: lib/email/templates/affiliate/payment-processed.tsx | H189: =C189=F189 -> TRUE
B190: =B189+1 -> 189 | C190: lib/email/templates/affiliate/welcome.tsx | E190: =E189+1 -> 189 | F190: lib/email/templates/affiliate/welcome.tsx | H190: =C190=F190 -> TRUE

Sheet Frontend NON-TSX
C1: 1 | D1: frontend/.env.example | F1: 1 | G1: =REPLACE(D1, 1, 10, "") -> .env.example
C2: 2 | D2: frontend/.env.sync-checklist | F2: =F1+1 -> 2 | G2: =REPLACE(D2, 1, 10, "") -> .env.sync-checklist
C3: 3 | D3: frontend/.eslintrc.json | F3: =F2+1 -> 3 | G3: =REPLACE(D3, 1, 10, "") -> .eslintrc.json
C4: 4 | D4: frontend/.gitignore | F4: =F3+1 -> 4 | G4: =REPLACE(D4, 1, 10, "") -> .gitignore
C5: 5 | D5: frontend/.prettierrc | F5: =F4+1 -> 5 | G5: =REPLACE(D5, 1, 10, "") -> .prettierrc
C6: 14 | D6: frontend/app/api/admin/affiliates/[id]/distribute-codes/route.ts | F6: =F5+1 -> 6 | G6: =REPLACE(D6, 1, 10, "") -> app/api/admin/affiliates/[id]/distribute-codes/route.ts
C7: 15 | D7: frontend/app/api/admin/affiliates/[id]/reactivate/route.ts | F7: =F6+1 -> 7 | G7: =REPLACE(D7, 1, 10, "") -> app/api/admin/affiliates/[id]/reactivate/route.ts
C8: 16 | D8: frontend/app/api/admin/affiliates/[id]/route.ts | F8: =F7+1 -> 8 | G8: =REPLACE(D8, 1, 10, "") -> app/api/admin/affiliates/[id]/route.ts
C9: 17 | D9: frontend/app/api/admin/affiliates/[id]/suspend/route.ts | F9: =F8+1 -> 9 | G9: =REPLACE(D9, 1, 10, "") -> app/api/admin/affiliates/[id]/suspend/route.ts
C10: 18 | D10: frontend/app/api/admin/affiliates/reports/code-inventory/route.ts | F10: =F9+1 -> 10 | G10: =REPLACE(D10, 1, 10, "") -> app/api/admin/affiliates/reports/code-inventory/route.ts
C11: 19 | D11: frontend/app/api/admin/affiliates/reports/commission-owings/route.ts | F11: =F10+1 -> 11 | G11: =REPLACE(D11, 1, 10, "") -> app/api/admin/affiliates/reports/commission-owings/route.ts
C12: 20 | D12: frontend/app/api/admin/affiliates/reports/profit-loss/route.ts | F12: =F11+1 -> 12 | G12: =REPLACE(D12, 1, 10, "") -> app/api/admin/affiliates/reports/profit-loss/route.ts
C13: 21 | D13: frontend/app/api/admin/affiliates/reports/sales-performance/route.ts | F13: =F12+1 -> 13 | G13: =REPLACE(D13, 1, 10, "") -> app/api/admin/affiliates/reports/sales-performance/route.ts
... C224: 236 | D224: frontend/vercel.json | F224: =F223+1 -> 224 | G224: =REPLACE(D224, 1, 10, "") -> vercel.json

Sheet Monolith NON-TSX
D2: 1 | E2: `app/api/admin/affiliates/[id]/distribute-codes/route.ts` | G2: 1 | H2: =TRIM(SUBSTITUTE(SUBSTITUTE(E2, LEFT(E2, FIND("app/", E2)-1), ""), "`", "")) -> app/api/admin/affiliates/[id]/distribute-codes/route.ts
D3: 2 | E3: `app/api/admin/affiliates/[id]/reactivate/route.ts` | G3: =G2+1 -> 2 | H3: =TRIM(SUBSTITUTE(SUBSTITUTE(E3, LEFT(E3, FIND("app/", E3)-1), ""), "`", "")) -> app/api/admin/affiliates/[id]/reactivate/route.ts
D4: 3 | E4: `app/api/admin/affiliates/[id]/route.ts` | G4: =G3+1 -> 3 | H4: =TRIM(SUBSTITUTE(SUBSTITUTE(E4, LEFT(E4, FIND("app/", E4)-1), ""), "`", "")) -> app/api/admin/affiliates/[id]/route.ts
D5: 4 | E5: `app/api/admin/affiliates/[id]/suspend/route.ts` | G5: =G4+1 -> 4 | H5: =TRIM(SUBSTITUTE(SUBSTITUTE(E5, LEFT(E5, FIND("app/", E5)-1), ""), "`", "")) -> app/api/admin/affiliates/[id]/suspend/route.ts
D6: 5 | E6: `app/api/admin/affiliates/reports/code-inventory/route.ts` | G6: =G5+1 -> 5 | H6: =TRIM(SUBSTITUTE(SUBSTITUTE(E6, LEFT(E6, FIND("app/", E6)-1), ""), "`", "")) -> app/api/admin/affiliates/reports/code-inventory/route.ts
D7: 6 | E7: `app/api/admin/affiliates/reports/commission-owings/route.ts` | G7: =G6+1 -> 6 | H7: =TRIM(SUBSTITUTE(SUBSTITUTE(E7, LEFT(E7, FIND("app/", E7)-1), ""), "`", "")) -> app/api/admin/affiliates/reports/commission-owings/route.ts
D8: 7 | E8: `app/api/admin/affiliates/reports/profit-loss/route.ts` | G8: =G7+1 -> 7 | H8: =TRIM(SUBSTITUTE(SUBSTITUTE(E8, LEFT(E8, FIND("app/", E8)-1), ""), "`", "")) -> app/api/admin/affiliates/reports/profit-loss/route.ts
D9: 8 | E9: `app/api/admin/affiliates/reports/sales-performance/route.ts` | G9: =G8+1 -> 8 | H9: =TRIM(SUBSTITUTE(SUBSTITUTE(E9, LEFT(E9, FIND("app/", E9)-1), ""), "`", "")) -> app/api/admin/affiliates/reports/sales-performance/route.ts
D10: 9 | E10: `app/api/admin/affiliates/route.ts` | G10: =G9+1 -> 9 | H10: =TRIM(SUBSTITUTE(SUBSTITUTE(E10, LEFT(E10, FIND("app/", E10)-1), ""), "`", "")) -> app/api/admin/affiliates/route.ts
D11: 10 | E11: `app/api/admin/analytics/route.ts` | G11: =G10+1 -> 10 | H11: =TRIM(SUBSTITUTE(SUBSTITUTE(E11, LEFT(E11, FIND("app/", E11)-1), ""), "`", "")) -> app/api/admin/analytics/route.ts
D12: 11 | E12: `app/api/admin/api-usage/route.ts` | G12: =G11+1 -> 11 | H12: =TRIM(SUBSTITUTE(SUBSTITUTE(E12, LEFT(E12, FIND("app/", E12)-1), ""), "`", "")) -> app/api/admin/api-usage/route.ts
D13: 12 | E13: `app/api/admin/codes/[code]/cancel/route.ts` | G13: =G12+1 -> 12 | H13: =TRIM(SUBSTITUTE(SUBSTITUTE(E13, LEFT(E13, FIND("app/", E13)-1), ""), "`", "")) -> app/api/admin/codes/[code]/cancel/route.ts
D14: 13 | E14: `app/api/admin/commissions/pay/route.ts` | G14: =G13+1 -> 13 | H14: =TRIM(SUBSTITUTE(SUBSTITUTE(E14, LEFT(E14, FIND("app/", E14)-1), ""), "`", "")) -> app/api/admin/commissions/pay/route.ts
... D102: 101 | E102: `app/globals.css` | G102: =G101+1 -> 101 | H102: =TRIM(SUBSTITUTE(SUBSTITUTE(E102, LEFT(E102, FIND("app/", E102)-1), ""), "`", "")) -> app/globals.css
D103: 1 | E103: `components/affiliate/index.ts` | G103: =G102+1 -> 102 | H103: =TRIM(SUBSTITUTE(SUBSTITUTE(E103, LEFT(E103, FIND("components/", E103)-1), ""), "`", "")) -> components/affiliate/index.ts
D104: 2 | E104: `components/payments/index.ts` | G104: =G103+1 -> 103 | H104: =TRIM(SUBSTITUTE(SUBSTITUTE(E104, LEFT(E104, FIND("components/", E104)-1), ""), "`", "")) -> components/payments/index.ts
D105: 1 | E105: `hooks/use-alerts.ts` | G105: =G104+1 -> 104 | H105: =TRIM(SUBSTITUTE(SUBSTITUTE(E105, LEFT(E105, FIND("hooks/", E105)-1), ""), "`", "")) -> hooks/use-alerts.ts
D106: 2 | E106: `hooks/use-auth.ts` | G106: =G105+1 -> 105 | H106: =TRIM(SUBSTITUTE(SUBSTITUTE(E106, LEFT(E106, FIND("hooks/", E106)-1), ""), "`", "")) -> hooks/use-auth.ts
D107: 3 | E107: `hooks/use-indicators.ts` | G107: =G106+1 -> 106 | H107: =TRIM(SUBSTITUTE(SUBSTITUTE(E107, LEFT(E107, FIND("hooks/", E107)-1), ""), "`", "")) -> hooks/use-indicators.ts
D108: 4 | E108: `hooks/use-login-tracking.ts` | G108: =G107+1 -> 107 | H108: =TRIM(SUBSTITUTE(SUBSTITUTE(E108, LEFT(E108, FIND("hooks/", E108)-1), ""), "`", "")) -> hooks/use-login-tracking.ts
D109: 5 | E109: `hooks/use-optimistic-mutation.ts` | G109: =G108+1 -> 108 | H109: =TRIM(SUBSTITUTE(SUBSTITUTE(E109, LEFT(E109, FIND("hooks/", E109)-1), ""), "`", "")) -> hooks/use-optimistic-mutation.ts
D110: 6 | E110: `hooks/use-toast.ts` | G110: =G109+1 -> 109 | H110: =TRIM(SUBSTITUTE(SUBSTITUTE(E110, LEFT(E110, FIND("hooks/", E110)-1), ""), "`", "")) -> hooks/use-toast.ts
D111: 7 | E111: `hooks/use-watchlist.ts` | G111: =G110+1 -> 110 | H111: =TRIM(SUBSTITUTE(SUBSTITUTE(E111, LEFT(E111, FIND("hooks/", E111)-1), ""), "`", "")) -> hooks/use-watchlist.ts
D112: 8 | E112: `hooks/use-websocket.ts` | G112: =G111+1 -> 111 | H112: =TRIM(SUBSTITUTE(SUBSTITUTE(E112, LEFT(E112, FIND("hooks/", E112)-1), ""), "`", "")) -> hooks/use-websocket.ts
D113: 1 | E113: `lib/admin/affiliate-management.ts` | G113: =G112+1 -> 112 | H113: =TRIM(SUBSTITUTE(SUBSTITUTE(E113, LEFT(E113, FIND("lib/", E113)-1), ""), "`", "")) -> lib/admin/affiliate-management.ts
D114: 2 | E114: `lib/admin/code-distribution.ts` | G114: =G113+1 -> 113 | H114: =TRIM(SUBSTITUTE(SUBSTITUTE(E114, LEFT(E114, FIND("lib/", E114)-1), ""), "`", "")) -> lib/admin/code-distribution.ts
D115: 3 | E115: `lib/admin/pnl-calculator.ts` | G115: =G114+1 -> 114 | H115: =TRIM(SUBSTITUTE(SUBSTITUTE(E115, LEFT(E115, FIND("lib/", E115)-1), ""), "`", "")) -> lib/admin/pnl-calculator.ts
D116: 4 | E116: `lib/affiliate/code-generator.ts` | G116: =G115+1 -> 115 | H116: =TRIM(SUBSTITUTE(SUBSTITUTE(E116, LEFT(E116, FIND("lib/", E116)-1), ""), "`", "")) -> lib/affiliate/code-generator.ts
D117: 5 | E117: `lib/affiliate/commission-calculator.ts` | G117: =G116+1 -> 116 | H117: =TRIM(SUBSTITUTE(SUBSTITUTE(E117, LEFT(E117, FIND("lib/", E117)-1), ""), "`", "")) -> lib/affiliate/commission-calculator.ts
D118: 6 | E118: `lib/affiliate/constants.ts` | G118: =G117+1 -> 117 | H118: =TRIM(SUBSTITUTE(SUBSTITUTE(E118, LEFT(E118, FIND("lib/", E118)-1), ""), "`", "")) -> lib/affiliate/constants.ts
D119: 7 | E119: `lib/affiliate/registration.ts` | G119: =G118+1 -> 118 | H119: =TRIM(SUBSTITUTE(SUBSTITUTE(E119, LEFT(E119, FIND("lib/", E119)-1), ""), "`", "")) -> lib/affiliate/registration.ts
D120: 8 | E120: `lib/affiliate/report-builder.ts` | G120: =G119+1 -> 119 | H120: =TRIM(SUBSTITUTE(SUBSTITUTE(E120, LEFT(E120, FIND("lib/", E120)-1), ""), "`", "")) -> lib/affiliate/report-builder.ts
D121: 9 | E121: `lib/affiliate/types.ts` | G121: =G120+1 -> 120 | H121: =TRIM(SUBSTITUTE(SUBSTITUTE(E121, LEFT(E121, FIND("lib/", E121)-1), ""), "`", "")) -> lib/affiliate/types.ts
D122: 10 | E122: `lib/affiliate/validators.ts` | G122: =G121+1 -> 121 | H122: =TRIM(SUBSTITUTE(SUBSTITUTE(E122, LEFT(E122, FIND("lib/", E122)-1), ""), "`", "")) -> lib/affiliate/validators.ts
D123: 11 | E123: `lib/api/index.ts` | G123: =G122+1 -> 122 | H123: =TRIM(SUBSTITUTE(SUBSTITUTE(E123, LEFT(E123, FIND("lib/", E123)-1), ""), "`", "")) -> lib/api/index.ts
D124: 12 | E124: `lib/api/mt5-client.ts` | G124: =G123+1 -> 123 | H124: =TRIM(SUBSTITUTE(SUBSTITUTE(E124, LEFT(E124, FIND("lib/", E124)-1), ""), "`", "")) -> lib/api/mt5-client.ts
... D199: 87 | E199: `lib/utils.ts` | G199: =G198+1 -> 198 | H199: =TRIM(SUBSTITUTE(SUBSTITUTE(E199, LEFT(E199, FIND("lib/", E199)-1), ""), "`", "")) -> lib/utils.ts
D200: 1 | E200: `prisma/migrations/20251227000000_init/migration.sql` | G200: =G199+1 -> 199 | H200: =TRIM(SUBSTITUTE(SUBSTITUTE(E200, LEFT(E200, FIND("prisma/", E200)-1), ""), "`", "")) -> prisma/migrations/20251227000000_init/migration.sql
D201: 2 | E201: `prisma/schema.prisma` | G201: =G200+1 -> 200 | H201: =TRIM(SUBSTITUTE(SUBSTITUTE(E201, LEFT(E201, FIND("prisma/", E201)-1), ""), "`", "")) -> prisma/schema.prisma
D202: 3 | E202: `prisma/seed.ts` | G202: =G201+1 -> 201 | H202: =TRIM(SUBSTITUTE(SUBSTITUTE(E202, LEFT(E202, FIND("prisma/", E202)-1), ""), "`", "")) -> prisma/seed.ts
D203: 1 | E203: `types/alert.ts` | G203: =G202+1 -> 202 | H203: =TRIM(SUBSTITUTE(SUBSTITUTE(E203, LEFT(E203, FIND("types/", E203)-1), ""), "`", "")) -> types/alert.ts
D204: 2 | E204: `types/api.ts` | G204: =G203+1 -> 203 | H204: =TRIM(SUBSTITUTE(SUBSTITUTE(E204, LEFT(E204, FIND("types/", E204)-1), ""), "`", "")) -> types/api.ts
D205: 3 | E205: `types/disbursement.ts` | G205: =G204+1 -> 204 | H205: =TRIM(SUBSTITUTE(SUBSTITUTE(E205, LEFT(E205, FIND("types/", E205)-1), ""), "`", "")) -> types/disbursement.ts
D206: 4 | E206: `types/dlocal.ts` | G206: =G205+1 -> 205 | H206: =TRIM(SUBSTITUTE(SUBSTITUTE(E206, LEFT(E206, FIND("types/", E206)-1), ""), "`", "")) -> types/dlocal.ts
D207: 5 | E207: `types/index.ts` | G207: =G206+1 -> 206 | H207: =TRIM(SUBSTITUTE(SUBSTITUTE(E207, LEFT(E207, FIND("types/", E207)-1), ""), "`", "")) -> types/index.ts
D208: 6 | E208: `types/indicator.ts` | G208: =G207+1 -> 207 | H208: =TRIM(SUBSTITUTE(SUBSTITUTE(E208, LEFT(E208, FIND("types/", E208)-1), ""), "`", "")) -> types/indicator.ts
D209: 7 | E209: `types/next-auth.d.ts` | G209: =G208+1 -> 208 | H209: =TRIM(SUBSTITUTE(SUBSTITUTE(E209, LEFT(E209, FIND("types/", E209)-1), ""), "`", "")) -> types/next-auth.d.ts
D210: 8 | E210: `types/payment.ts` | G210: =G209+1 -> 209 | H210: =TRIM(SUBSTITUTE(SUBSTITUTE(E210, LEFT(E210, FIND("types/", E210)-1), ""), "`", "")) -> types/payment.ts
D211: 9 | E211: `types/prisma-stubs.d.ts` | G211: =G210+1 -> 210 | H211: =TRIM(SUBSTITUTE(SUBSTITUTE(E211, LEFT(E211, FIND("types/", E211)-1), ""), "`", "")) -> types/prisma-stubs.d.ts
D212: 10 | E212: `types/tier.ts` | G212: =G211+1 -> 211 | H212: =TRIM(SUBSTITUTE(SUBSTITUTE(E212, LEFT(E212, FIND("types/", E212)-1), ""), "`", "")) -> types/tier.ts
D213: 11 | E213: `types/user.ts` | G213: =G212+1 -> 212 | H213: =TRIM(SUBSTITUTE(SUBSTITUTE(E213, LEFT(E213, FIND("types/", E213)-1), ""), "`", "")) -> types/user.ts
D214: 12 | E214: `types/watchlist.ts` | G214: =G213+1 -> 213 | H214: =TRIM(SUBSTITUTE(SUBSTITUTE(E214, LEFT(E214, FIND("types/", E214)-1), ""), "`", "")) -> types/watchlist.ts
D215: 1 | E215: `oauth/claude-code-oauth-integration-task.md` | G215: =G214+1 -> 214 | H215: =TRIM(SUBSTITUTE(SUBSTITUTE(E215, LEFT(E215, FIND("oauth/", E215)-1), ""), "`", "")) -> oauth/claude-code-oauth-integration-task.md
D216: 2 | E216: `oauth/google-oauth-implementation-guide.md` | G216: =G215+1 -> 215 | H216: =TRIM(SUBSTITUTE(SUBSTITUTE(E216, LEFT(E216, FIND("oauth/", E216)-1), ""), "`", "")) -> oauth/google-oauth-implementation-guide.md
D217: 3 | E217: `oauth/oauth-decision-request.md` | G217: =G216+1 -> 216 | H217: =TRIM(SUBSTITUTE(SUBSTITUTE(E217, LEFT(E217, FIND("oauth/", E217)-1), ""), "`", "")) -> oauth/oauth-decision-request.md
D218: 1 | E218: `middleware/tier-check.ts` | G218: =G217+1 -> 217 | H218: =TRIM(SUBSTITUTE(SUBSTITUTE(E218, LEFT(E218, FIND("middleware/", E218)-1), ""), "`", "")) -> middleware/tier-check.ts
D219: 1 | E219: `emails/index.ts` | G219: =G218+1 -> 218 | H219: =TRIM(SUBSTITUTE(SUBSTITUTE(E219, LEFT(E219, FIND("emails/", E219)-1), ""), "`", "")) -> emails/index.ts
D220: 1 | E220: `__tests__/api/admin-affiliates.test.ts` | G220: =G219+1 -> 219 | H220: =TRIM(SUBSTITUTE(SUBSTITUTE(E220, LEFT(E220, FIND("__tests__/", E220)-1), ""), "`", "")) -> __tests__/api/admin-affiliates.test.ts
D221: 2 | E221: `__tests__/api/admin-reports.test.ts` | G221: =G220+1 -> 220 | H221: =TRIM(SUBSTITUTE(SUBSTITUTE(E221, LEFT(E221, FIND("__tests__/", E221)-1), ""), "`", "")) -> __tests__/api/admin-reports.test.ts
D222: 3 | E222: `__tests__/api/admin.test.ts` | G222: =G221+1 -> 221 | H222: =TRIM(SUBSTITUTE(SUBSTITUTE(E222, LEFT(E222, FIND("__tests__/", E222)-1), ""), "`", "")) -> __tests__/api/admin.test.ts
D223: 4 | E223: `__tests__/api/affiliate-conversion.test.ts` | G223: =G222+1 -> 222 | H223: =TRIM(SUBSTITUTE(SUBSTITUTE(E223, LEFT(E223, FIND("__tests__/", E223)-1), ""), "`", "")) -> __tests__/api/affiliate-conversion.test.ts
D224: 5 | E224: `__tests__/api/affiliate-dashboard.test.ts` | G224: =G223+1 -> 223 | H224: =TRIM(SUBSTITUTE(SUBSTITUTE(E224, LEFT(E224, FIND("__tests__/", E224)-1), ""), "`", "")) -> __tests__/api/affiliate-dashboard.test.ts
D225: 6 | E225: `__tests__/api/affiliate-registration.test.ts` | G225: =G224+1 -> 224 | H225: =TRIM(SUBSTITUTE(SUBSTITUTE(E225, LEFT(E225, FIND("__tests__/", E225)-1), ""), "`", "")) -> __tests__/api/affiliate-registration.test.ts
D226: 7 | E226: `__tests__/api/alerts.test.ts` | G226: =G225+1 -> 225 | H226: =TRIM(SUBSTITUTE(SUBSTITUTE(E226, LEFT(E226, FIND("__tests__/", E226)-1), ""), "`", "")) -> __tests__/api/alerts.test.ts
D227: 8 | E227: `__tests__/api/notifications.test.ts` | G227: =G226+1 -> 226 | H227: =TRIM(SUBSTITUTE(SUBSTITUTE(E227, LEFT(E227, FIND("__tests__/", E227)-1), ""), "`", "")) -> __tests__/api/notifications.test.ts
D228: 9 | E228: `__tests__/api/tier.test.ts` | G228: =G227+1 -> 227 | H228: =TRIM(SUBSTITUTE(SUBSTITUTE(E228, LEFT(E228, FIND("__tests__/", E228)-1), ""), "`", "")) -> __tests__/api/tier.test.ts
D229: 10 | E229: `__tests__/api/user.test.ts` | G229: =G228+1 -> 228 | H229: =TRIM(SUBSTITUTE(SUBSTITUTE(E229, LEFT(E229, FIND("__tests__/", E229)-1), ""), "`", "")) -> __tests__/api/user.test.ts
D230: 11 | E230: `__tests__/api/watchlist.test.ts` | G230: =G229+1 -> 229 | H230: =TRIM(SUBSTITUTE(SUBSTITUTE(E230, LEFT(E230, FIND("__tests__/", E230)-1), ""), "`", "")) -> __tests__/api/watchlist.test.ts
D231: 12 | E231: `__tests__/api/cron-jobs.test.ts` | G231: =G230+1 -> 230 | H231: =TRIM(SUBSTITUTE(SUBSTITUTE(E231, LEFT(E231, FIND("__tests__/", E231)-1), ""), "`", "")) -> __tests__/api/cron-jobs.test.ts
... D303: 84 | E303: `__tests__/setup.ts` | G303: =G302+1 -> 302 | H303: =TRIM(SUBSTITUTE(SUBSTITUTE(E303, LEFT(E303, FIND("__tests__/", E303)-1), ""), "`", "")) -> __tests__/setup.ts

Sheet Frontend-Monolith NON-TSX
C1: FRONTEND | F1: MONOLITH | H1: Matched
B2: 1 | E2: 1 | F2: __tests__/api/admin.test.ts | H2: =C2=F2 -> FALSE
B3: =B2+1 -> 2 | E3: =E2+1 -> 2 | F3: __tests__/api/admin-affiliates.test.ts | H3: =C3=F3 -> FALSE
B4: =B3+1 -> 3 | E4: =E3+1 -> 3 | F4: __tests__/api/admin-reports.test.ts | H4: =C4=F4 -> FALSE
B5: =B4+1 -> 4 | E5: =E4+1 -> 4 | F5: __tests__/api/affiliate-conversion.test.ts | H5: =C5=F5 -> FALSE
B6: =B5+1 -> 5 | E6: =E5+1 -> 5 | F6: __tests__/api/affiliate-dashboard.test.ts | H6: =C6=F6 -> FALSE
B7: =B6+1 -> 6 | E7: =E6+1 -> 6 | F7: __tests__/api/affiliate-registration.test.ts | H7: =C7=F7 -> FALSE
B8: =B7+1 -> 7 | E8: =E7+1 -> 7 | F8: __tests__/api/alerts.test.ts | H8: =C8=F8 -> FALSE
B9: =B8+1 -> 8 | E9: =E8+1 -> 8 | F9: __tests__/api/cron/process-pending.test.ts | H9: =C9=F9 -> FALSE
B10: =B9+1 -> 9 | E10: =E9+1 -> 9 | F10: __tests__/api/cron-jobs.test.ts | H10: =C10=F10 -> FALSE
B11: =B10+1 -> 10 | E11: =E10+1 -> 10 | F11: __tests__/api/disbursement/affiliates.test.ts | H11: =C11=F11 -> FALSE
B12: =B11+1 -> 11 | E12: =E11+1 -> 11 | F12: __tests__/api/disbursement/audit.test.ts | H12: =C12=F12 -> FALSE
B13: =B12+1 -> 12 | E13: =E12+1 -> 12 | F13: __tests__/api/disbursement/batches.test.ts | H13: =C13=F13 -> FALSE
B14: =B13+1 -> 13 | E14: =E13+1 -> 13 | F14: __tests__/api/disbursement/execute.test.ts | H14: =C14=F14 -> FALSE
... B85: =B84+1 -> 84 | E85: =E84+1 -> 84 | F85: __tests__/types/types.test.ts | H85: =C85=F85 -> FALSE
B86: =B85+1 -> 85 | C86: app/api/admin/affiliates/[id]/distribute-codes/route.ts | E86: =E85+1 -> 85 | F86: app/api/admin/affiliates/[id]/distribute-codes/route.ts | H86: =C86=F86 -> TRUE
B87: =B86+1 -> 86 | C87: app/api/admin/affiliates/[id]/reactivate/route.ts | E87: =E86+1 -> 86 | F87: app/api/admin/affiliates/[id]/reactivate/route.ts | H87: =C87=F87 -> TRUE
B88: =B87+1 -> 87 | C88: app/api/admin/affiliates/[id]/route.ts | E88: =E87+1 -> 87 | F88: app/api/admin/affiliates/[id]/route.ts | H88: =C88=F88 -> TRUE
B89: =B88+1 -> 88 | C89: app/api/admin/affiliates/[id]/suspend/route.ts | E89: =E88+1 -> 88 | F89: app/api/admin/affiliates/[id]/suspend/route.ts | H89: =C89=F89 -> TRUE
B90: =B89+1 -> 89 | C90: app/api/admin/affiliates/reports/code-inventory/route.ts | E90: =E89+1 -> 89 | F90: app/api/admin/affiliates/reports/code-inventory/route.ts | H90: =C90=F90 -> TRUE
B91: =B90+1 -> 90 | C91: app/api/admin/affiliates/reports/commission-owings/route.ts | E91: =E90+1 -> 90 | F91: app/api/admin/affiliates/reports/commission-owings/route.ts | H91: =C91=F91 -> TRUE
B92: =B91+1 -> 91 | C92: app/api/admin/affiliates/reports/profit-loss/route.ts | E92: =E91+1 -> 91 | F92: app/api/admin/affiliates/reports/profit-loss/route.ts | H92: =C92=F92 -> TRUE
B93: =B92+1 -> 92 | C93: app/api/admin/affiliates/reports/sales-performance/route.ts | E93: =E92+1 -> 92 | F93: app/api/admin/affiliates/reports/sales-performance/route.ts | H93: =C93=F93 -> TRUE
B94: =B93+1 -> 93 | C94: app/api/admin/affiliates/route.ts | E94: =E93+1 -> 93 | F94: app/api/admin/affiliates/route.ts | H94: =C94=F94 -> TRUE
B95: =B94+1 -> 94 | C95: app/api/admin/analytics/route.ts | E95: =E94+1 -> 94 | F95: app/api/admin/analytics/route.ts | H95: =C95=F95 -> TRUE
B96: =B95+1 -> 95 | C96: app/api/admin/api-usage/route.ts | E96: =E95+1 -> 95 | F96: app/api/admin/api-usage/route.ts | H96: =C96=F96 -> TRUE
B97: =B96+1 -> 96 | C97: app/api/admin/codes/[code]/cancel/route.ts | E97: =E96+1 -> 96 | F97: app/api/admin/codes/[code]/cancel/route.ts | H97: =C97=F97 -> TRUE
... B120: =B119+1 -> 119 | C120: app/api/auth/verify-email/route.ts | E120: =E119+1 -> 119 | F120: app/api/auth/verify-email/route.ts | H120: =C120=F120 -> TRUE
B121: =B120+1 -> 120 | E121: =E120+1 -> 120 | F121: app/api/candles/[symbol]/route.ts | H121: =C121=F121 -> FALSE
B122: =B121+1 -> 121 | C122: app/api/checkout/route.ts | E122: =E121+1 -> 121 | F122: app/api/checkout/route.ts | H122: =C122=F122 -> TRUE
B123: =B122+1 -> 122 | C123: app/api/checkout/validate-code/route.ts | E123: =E122+1 -> 122 | F123: app/api/checkout/validate-code/route.ts | H123: =C123=F123 -> TRUE
B124: =B123+1 -> 123 | C124: app/api/config/affiliate/route.ts | E124: =E123+1 -> 123 | F124: app/api/config/affiliate/route.ts | H124: =C124=F124 -> TRUE
B125: =B124+1 -> 124 | C125: app/api/cron/check-expiring-subscriptions/route.ts | E125: =E124+1 -> 124 | F125: app/api/cron/check-expiring-subscriptions/route.ts | H125: =C125=F125 -> TRUE
B126: =B125+1 -> 125 | C126: app/api/cron/daily-maintenance/route.ts | E126: =E125+1 -> 125 | F126: app/api/cron/daily-maintenance/route.ts | H126: =C126=F126 -> TRUE
B127: =B126+1 -> 126 | C127: app/api/cron/distribute-codes/route.ts | E127: =E126+1 -> 126 | F127: app/api/cron/distribute-codes/route.ts | H127: =C127=F127 -> TRUE
B128: =B127+1 -> 127 | C128: app/api/cron/downgrade-expired-subscriptions/route.ts | E128: =E127+1 -> 127 | F128: app/api/cron/downgrade-expired-subscriptions/route.ts | H128: =C128=F128 -> TRUE
B129: =B128+1 -> 128 | C129: app/api/cron/expire-codes/route.ts | E129: =E128+1 -> 128 | F129: app/api/cron/expire-codes/route.ts | H129: =C129=F129 -> TRUE
B130: =B129+1 -> 129 | C130: app/api/cron/process-pending-disbursements/route.ts | E130: =E129+1 -> 129 | F130: app/api/cron/process-pending-disbursements/route.ts | H130: =C130=F130 -> TRUE
B131: =B130+1 -> 130 | C131: app/api/cron/send-monthly-reports/route.ts | E131: =E130+1 -> 130 | F131: app/api/cron/send-monthly-reports/route.ts | H131: =C131=F131 -> TRUE
B132: =B131+1 -> 131 | C132: app/api/cron/sync-riseworks-accounts/route.ts | E132: =E131+1 -> 131 | F132: app/api/cron/sync-riseworks-accounts/route.ts | H132: =C132=F132 -> TRUE
B133: =B132+1 -> 132 | C133: app/api/disbursement/affiliates/[affiliateId]/commissions/route.ts | E133: =E132+1 -> 132 | F133: app/api/disbursement/affiliates/[affiliateId]/commissions/route.ts | H133: =C133=F133 -> TRUE
... B210: =B209+1 -> 209 | C210: lib/api/mt5-transform.ts | E210: =E209+1 -> 209 | F210: lib/api/mt5-transform.ts | H210: =C210=F210 -> TRUE
B211: =B210+1 -> 210 | C211: lib/api-client.test.example.ts | E211: =E210+1 -> 210 | H211: =C211=F211 -> FALSE
B212: =B211+1 -> 211 | C212: lib/api-client.ts | E212: =E211+1 -> 211 | H212: =C212=F212 -> FALSE
B213: =B212+1 -> 212 | C213: lib/auth/auth-options.ts | E213: =E212+1 -> 212 | F213: lib/auth/auth-options.ts | H213: =C213=F213 -> TRUE
B214: =B213+1 -> 213 | C214: lib/auth/errors.ts | E214: =E213+1 -> 213 | F214: lib/auth/errors.ts | H214: =C214=F214 -> TRUE
B215: =B214+1 -> 214 | C215: lib/auth/permissions.ts | E215: =E214+1 -> 214 | F215: lib/auth/permissions.ts | H215: =C215=F215 -> TRUE
B216: =B215+1 -> 215 | C216: lib/auth/session.ts | E216: =E215+1 -> 215 | F216: lib/auth/session.ts | H216: =C216=F216 -> TRUE
B217: =B216+1 -> 216 | C217: lib/auth/session-tracker.ts | E217: =E216+1 -> 216 | F217: lib/auth/session-tracker.ts | H217: =C217=F217 -> TRUE
B218: =B217+1 -> 217 | C218: lib/auth/two-factor.ts | E218: =E217+1 -> 217 | F218: lib/auth/two-factor.ts | H218: =C218=F218 -> TRUE
B219: =B218+1 -> 218 | C219: lib/cache/cache-manager.ts | E219: =E218+1 -> 218 | F219: lib/cache/cache-manager.ts | H219: =C219=F219 -> TRUE
B220: =B219+1 -> 219 | E220: =E219+1 -> 219 | F220: lib/candle-data-helpers.ts | H220: =C220=F220 -> FALSE
B221: =B220+1 -> 220 | C221: lib/constants/business-rules.ts | E221: =E220+1 -> 220 | F221: lib/constants/business-rules.ts | H221: =C221=F221 -> TRUE
B222: =B221+1 -> 221 | C222: lib/cron/check-expiring-subscriptions.ts | E222: =E221+1 -> 221 | F222: lib/cron/check-expiring-subscriptions.ts | H222: =C222=F222 -> TRUE
B223: =B222+1 -> 222 | C223: lib/cron/downgrade-expired-subscriptions.ts | E223: =E222+1 -> 222 | F223: lib/cron/downgrade-expired-subscriptions.ts | H223: =C223=F223 -> TRUE
B224: =B223+1 -> 223 | C224: lib/cron/monthly-distribution.ts | E224: =E223+1 -> 223 | F224: lib/cron/monthly-distribution.ts | H224: =C224=F224 -> TRUE
B225: =B224+1 -> 224 | C225: lib/csrf.ts | E225: =E224+1 -> 224 | F225: lib/csrf.ts | H225: =C225=F225 -> TRUE
B226: =B225+1 -> 225 | C226: lib/db/prisma.ts | E226: =E225+1 -> 225 | F226: lib/db/prisma.ts | H226: =C226=F226 -> TRUE
B227: =B226+1 -> 226 | C227: lib/db/seed.ts | E227: =E226+1 -> 226 | F227: lib/db/seed.ts | H227: =C227=F227 -> TRUE
B228: =B227+1 -> 227 | C228: lib/disbursement/constants.ts | E228: =E227+1 -> 227 | F228: lib/disbursement/constants.ts | H228: =C228=F228 -> TRUE
B229: =B228+1 -> 228 | C229: lib/disbursement/cron/disbursement-processor.ts | E229: =E228+1 -> 228 | F229: lib/disbursement/cron/disbursement-processor.ts | H229: =C229=F229 -> TRUE
B230: =B229+1 -> 229 | C230: lib/disbursement/providers/base-provider.ts | E230: =E229+1 -> 229 | F230: lib/disbursement/providers/base-provider.ts | H230: =C230=F230 -> TRUE
B231: =B230+1 -> 230 | C231: lib/disbursement/providers/mock-provider.ts | E231: =E230+1 -> 230 | F231: lib/disbursement/providers/mock-provider.ts | H231: =C231=F231 -> TRUE
B232: =B231+1 -> 231 | C232: lib/disbursement/providers/provider-factory.ts | E232: =E231+1 -> 231 | F232: lib/disbursement/providers/provider-factory.ts | H232: =C232=F232 -> TRUE
... B267: =B266+1 -> 266 | C267: lib/stripe/webhook-handlers.ts | E267: =E266+1 -> 266 | F267: lib/stripe/webhook-handlers.ts | H267: =C267=F267 -> TRUE
B268: =B267+1 -> 267 | E268: =E267+1 -> 267 | F268: lib/tier/__tests__/constants.test.ts | H268: =C268=F268 -> FALSE
B269: =B268+1 -> 268 | E269: =E268+1 -> 268 | F269: lib/tier/__tests__/validator.test.ts | H269: =C269=F269 -> FALSE
B270: =B269+1 -> 269 | C270: lib/tier/constants.ts | E270: =E269+1 -> 269 | F270: lib/tier/constants.ts | H270: =C270=F270 -> TRUE
B271: =B270+1 -> 270 | C271: lib/tier/index.ts | E271: =E270+1 -> 270 | F271: lib/tier/index.ts | H271: =C271=F271 -> TRUE
B272: =B271+1 -> 271 | C272: lib/tier/validator.ts | E272: =E271+1 -> 271 | F272: lib/tier/validator.ts | H272: =C272=F272 -> TRUE
B273: =B272+1 -> 272 | C273: lib/tier-config.ts | E273: =E272+1 -> 272 | F273: lib/tier-config.ts | H273: =C273=F273 -> TRUE
B274: =B273+1 -> 273 | C274: lib/tier-helpers.ts | E274: =E273+1 -> 273 | F274: lib/tier-helpers.ts | H274: =C274=F274 -> TRUE
B275: =B274+1 -> 274 | C275: lib/tier-validation.ts | E275: =E274+1 -> 274 | F275: lib/tier-validation.ts | H275: =C275=F275 -> TRUE
B276: =B275+1 -> 275 | C276: lib/tokens.ts | E276: =E275+1 -> 275 | F276: lib/tokens.ts | H276: =C276=F276 -> TRUE
B277: =B276+1 -> 276 | C277: lib/utils.ts | E277: =E276+1 -> 276 | F277: lib/utils.ts | H277: =C277=F277 -> TRUE
B278: =B277+1 -> 277 | C278: lib/utils/constants.ts | E278: =E277+1 -> 277 | F278: lib/utils/constants.ts | H278: =C278=F278 -> TRUE
B279: =B278+1 -> 278 | C279: lib/utils/formatters.ts | E279: =E278+1 -> 278 | F279: lib/utils/formatters.ts | H279: =C279=F279 -> TRUE
B280: =B279+1 -> 279 | C280: lib/utils/helpers.ts | E280: =E279+1 -> 279 | F280: lib/utils/helpers.ts | H280: =C280=F280 -> TRUE
B281: =B280+1 -> 280 | C281: lib/validations/alert.ts | E281: =E280+1 -> 280 | F281: lib/validations/alert.ts | H281: =C281=F281 -> TRUE
... B285: =B284+1 -> 284 | C285: lib/websocket/server.ts | E285: =E284+1 -> 284 | F285: lib/websocket/server.ts | H285: =C285=F285 -> TRUE
B286: =B285+1 -> 285 | C286: next.config.js | E286: =E285+1 -> 285 | H286: =C286=F286 -> FALSE
B287: =B286+1 -> 286 | C287: package.json | E287: =E286+1 -> 286 | H287: =C287=F287 -> FALSE
B288: =B287+1 -> 287 | C288: postcss.config.js | E288: =E287+1 -> 287 | H288: =C288=F288 -> FALSE
B289: =B288+1 -> 288 | E289: =E288+1 -> 288 | F289: lib/websocket/use-mt5-websocket.ts | H289: =C289=F289 -> FALSE
B290: =B289+1 -> 289 | E290: =E289+1 -> 289 | F290: middleware/tier-check.ts | H290: =C290=F290 -> FALSE
B291: =B290+1 -> 290 | C291: prisma/migrations/20251227000000_init/migration.sql | E291: =E290+1 -> 290 | F291: prisma/migrations/20251227000000_init/migration.sql | H291: =C291=F291 -> TRUE
B292: =B291+1 -> 291 | C292: prisma/schema.prisma | E292: =E291+1 -> 291 | F292: prisma/schema.prisma | H292: =C292=F292 -> TRUE
B293: =B292+1 -> 292 | C293: prisma/seed.ts | E293: =E292+1 -> 292 | F293: prisma/seed.ts | H293: =C293=F293 -> TRUE
B294: =B293+1 -> 293 | C294: public/manifest.json | E294: =E293+1 -> 293 | H294: =C294=F294 -> FALSE
B295: =B294+1 -> 294 | C295: scripts/verify-auth-config.js | E295: =E294+1 -> 294 | H295: =C295=F295 -> FALSE
B296: =B295+1 -> 295 | C296: tailwind.config.ts | E296: =E295+1 -> 295 | H296: =C296=F296 -> FALSE
B297: =B296+1 -> 296 | C297: tsconfig.json | E297: =E296+1 -> 296 | H297: =C297=F297 -> FALSE
B298: =B297+1 -> 297 | C298: types/alert.ts | E298: =E297+1 -> 297 | F298: types/alert.ts | H298: =C298=F298 -> TRUE
B299: =B298+1 -> 298 | C299: types/api.ts | E299: =E298+1 -> 298 | F299: types/api.ts | H299: =C299=F299 -> TRUE
B300: =B299+1 -> 299 | C300: types/disbursement.ts | E300: =E299+1 -> 299 | F300: types/disbursement.ts | H300: =C300=F300 -> TRUE
B301: =B300+1 -> 300 | C301: types/dlocal.ts | E301: =E300+1 -> 300 | F301: types/dlocal.ts | H301: =C301=F301 -> TRUE
B302: =B301+1 -> 301 | C302: types/index.ts | E302: =E301+1 -> 301 | F302: types/index.ts | H302: =C302=F302 -> TRUE
B303: =B302+1 -> 302 | C303: types/indicator.ts | E303: =E302+1 -> 302 | F303: types/indicator.ts | H303: =C303=F303 -> TRUE
B304: =B303+1 -> 303 | C304: types/next-auth.d.ts | E304: =E303+1 -> 303 | F304: types/next-auth.d.ts | H304: =C304=F304 -> TRUE
B305: =B304+1 -> 304 | C305: types/payment.ts | E305: =E304+1 -> 304 | F305: types/payment.ts | H305: =C305=F305 -> TRUE
...

Sheet Exhaustive List of Files
A1: 1 | B1: __tests__/api/admin.test.ts | C1: =VLOOKUP(B1,'BACKEND FILES'!A:B,2,FALSE) -> #N/A | D1: =VLOOKUP(B1,'FRONTEND FILES'!A:B,2,FALSE) -> #N/A | E1: =VLOOKUP(B1,'SHARED FILES'!A:B,2,FALSE) -> #N/A | F1: =_xlfn.IFNA(C1, _xlfn.IFNA(D1, _xlfn.IFNA(E1, "")))
A2: =A1+1 -> 2 | B2: __tests__/api/admin-affiliates.test.ts | C2: =VLOOKUP(B2,'BACKEND FILES'!A:B,2,FALSE) -> #N/A | D2: =VLOOKUP(B2,'FRONTEND FILES'!A:B,2,FALSE) -> #N/A | E2: =VLOOKUP(B2,'SHARED FILES'!A:B,2,FALSE) -> #N/A | F2: =_xlfn.IFNA(C2, _xlfn.IFNA(D2, _xlfn.IFNA(E2, "")))
A3: =A2+1 -> 3 | B3: __tests__/api/admin-reports.test.ts | C3: =VLOOKUP(B3,'BACKEND FILES'!A:B,2,FALSE) -> #N/A | D3: =VLOOKUP(B3,'FRONTEND FILES'!A:B,2,FALSE) -> #N/A | E3: =VLOOKUP(B3,'SHARED FILES'!A:B,2,FALSE) -> #N/A | F3: =_xlfn.IFNA(C3, _xlfn.IFNA(D3, _xlfn.IFNA(E3, "")))
A4: =A3+1 -> 4 | B4: __tests__/api/affiliate-conversion.test.ts | C4: =VLOOKUP(B4,'BACKEND FILES'!A:B,2,FALSE) -> #N/A | D4: =VLOOKUP(B4,'FRONTEND FILES'!A:B,2,FALSE) -> #N/A | E4: =VLOOKUP(B4,'SHARED FILES'!A:B,2,FALSE) -> #N/A | F4: =_xlfn.IFNA(C4, _xlfn.IFNA(D4, _xlfn.IFNA(E4, "")))
A5: =A4+1 -> 5 | B5: __tests__/api/affiliate-dashboard.test.ts | C5: =VLOOKUP(B5,'BACKEND FILES'!A:B,2,FALSE) -> #N/A | D5: =VLOOKUP(B5,'FRONTEND FILES'!A:B,2,FALSE) -> #N/A | E5: =VLOOKUP(B5,'SHARED FILES'!A:B,2,FALSE) -> #N/A | F5: =_xlfn.IFNA(C5, _xlfn.IFNA(D5, _xlfn.IFNA(E5, "")))
A6: =A5+1 -> 6 | B6: __tests__/api/affiliate-registration.test.ts | C6: =VLOOKUP(B6,'BACKEND FILES'!A:B,2,FALSE) -> #N/A | D6: =VLOOKUP(B6,'FRONTEND FILES'!A:B,2,FALSE) -> #N/A | E6: =VLOOKUP(B6,'SHARED FILES'!A:B,2,FALSE) -> #N/A | F6: =_xlfn.IFNA(C6, _xlfn.IFNA(D6, _xlfn.IFNA(E6, "")))
A7: =A6+1 -> 7 | B7: __tests__/api/alerts.test.ts | C7: =VLOOKUP(B7,'BACKEND FILES'!A:B,2,FALSE) -> #N/A | D7: =VLOOKUP(B7,'FRONTEND FILES'!A:B,2,FALSE) -> #N/A | E7: =VLOOKUP(B7,'SHARED FILES'!A:B,2,FALSE) -> #N/A | F7: =_xlfn.IFNA(C7, _xlfn.IFNA(D7, _xlfn.IFNA(E7, "")))
A8: =A7+1 -> 8 | B8: __tests__/api/cron/process-pending.test.ts | C8: =VLOOKUP(B8,'BACKEND FILES'!A:B,2,FALSE) -> #N/A | D8: =VLOOKUP(B8,'FRONTEND FILES'!A:B,2,FALSE) -> #N/A | E8: =VLOOKUP(B8,'SHARED FILES'!A:B,2,FALSE) -> #N/A | F8: =_xlfn.IFNA(C8, _xlfn.IFNA(D8, _xlfn.IFNA(E8, "")))
A9: =A8+1 -> 9 | B9: __tests__/api/cron-jobs.test.ts | C9: =VLOOKUP(B9,'BACKEND FILES'!A:B,2,FALSE) -> #N/A | D9: =VLOOKUP(B9,'FRONTEND FILES'!A:B,2,FALSE) -> #N/A | E9: =VLOOKUP(B9,'SHARED FILES'!A:B,2,FALSE) -> #N/A | F9: =_xlfn.IFNA(C9, _xlfn.IFNA(D9, _xlfn.IFNA(E9, "")))
A10: =A9+1 -> 10 | B10: __tests__/api/disbursement/affiliates.test.ts | C10: =VLOOKUP(B10,'BACKEND FILES'!A:B,2,FALSE) -> #N/A | D10: =VLOOKUP(B10,'FRONTEND FILES'!A:B,2,FALSE) -> #N/A | E10: =VLOOKUP(B10,'SHARED FILES'!A:B,2,FALSE) -> #N/A | F10: =_xlfn.IFNA(C10, _xlfn.IFNA(D10, _xlfn.IFNA(E10, "")))
A11: =A10+1 -> 11 | B11: __tests__/api/disbursement/audit.test.ts | C11: =VLOOKUP(B11,'BACKEND FILES'!A:B,2,FALSE) -> #N/A | D11: =VLOOKUP(B11,'FRONTEND FILES'!A:B,2,FALSE) -> #N/A | E11: =VLOOKUP(B11,'SHARED FILES'!A:B,2,FALSE) -> #N/A | F11: =_xlfn.IFNA(C11, _xlfn.IFNA(D11, _xlfn.IFNA(E11, "")))
A12: =A11+1 -> 12 | B12: __tests__/api/disbursement/batches.test.ts | C12: =VLOOKUP(B12,'BACKEND FILES'!A:B,2,FALSE) -> #N/A | D12: =VLOOKUP(B12,'FRONTEND FILES'!A:B,2,FALSE) -> #N/A | E12: =VLOOKUP(B12,'SHARED FILES'!A:B,2,FALSE) -> #N/A | F12: =_xlfn.IFNA(C12, _xlfn.IFNA(D12, _xlfn.IFNA(E12, "")))
A13: =A12+1 -> 13 | B13: __tests__/api/disbursement/execute.test.ts | C13: =VLOOKUP(B13,'BACKEND FILES'!A:B,2,FALSE) -> #N/A | D13: =VLOOKUP(B13,'FRONTEND FILES'!A:B,2,FALSE) -> #N/A | E13: =VLOOKUP(B13,'SHARED FILES'!A:B,2,FALSE) -> #N/A | F13: =_xlfn.IFNA(C13, _xlfn.IFNA(D13, _xlfn.IFNA(E13, "")))
... A523: =A522+1 -> 523 | B523: vercel.json | C523: =VLOOKUP(B523,'BACKEND FILES'!A:B,2,FALSE) -> #N/A | D523: =VLOOKUP(B523,'FRONTEND FILES'!A:B,2,FALSE) -> #N/A | E523: =VLOOKUP(B523,'SHARED FILES'!A:B,2,FALSE) -> #N/A | F523: =_xlfn.IFNA(C523, _xlfn.IFNA(D523, _xlfn.IFNA(E523, "")))

Sheet BACKEND FILES
A1: app/api/admin/affiliates/[id]/distribute-codes/route.ts | B1: BACKEND
A2: app/api/admin/affiliates/[id]/reactivate/route.ts | B2: BACKEND
A3: app/api/admin/affiliates/[id]/route.ts | B3: BACKEND
A4: app/api/admin/affiliates/[id]/suspend/route.ts | B4: BACKEND
A5: app/api/admin/affiliates/reports/code-inventory/route.ts | B5: BACKEND
A6: app/api/admin/affiliates/reports/commission-owings/route.ts | B6: BACKEND
A7: app/api/admin/affiliates/reports/profit-loss/route.ts | B7: BACKEND
A8: app/api/admin/affiliates/reports/sales-performance/route.ts | B8: BACKEND
A9: app/api/admin/affiliates/route.ts | B9: BACKEND
A10: app/api/admin/analytics/route.ts | B10: BACKEND
A11: app/api/admin/api-usage/route.ts | B11: BACKEND
A12: app/api/admin/codes/[code]/cancel/route.ts | B12: BACKEND
... A195: prisma/seed.ts | B195: BACKEND

Sheet FRONTEND FILES
A1: app/(auth)/register/page.tsx | B1: FRONTEND
A2: app/(auth)/reset-password/page.tsx | B2: FRONTEND
A3: app/(auth)/verify-2fa/page.tsx | B3: FRONTEND
A4: app/(auth)/verify-email/page.tsx | B4: FRONTEND
A5: app/(auth)/verify-email/pending/page.tsx | B5: FRONTEND
A6: app/(dashboard)/**/*.tsx files | B6: FRONTEND
A7: app/(marketing)/landing-content.tsx | B7: FRONTEND
A8: app/(marketing)/layout.tsx | B8: FRONTEND
A9: app/(marketing)/page.tsx | B9: FRONTEND
A10: app/(marketing)/pricing/page.tsx | B10: FRONTEND
A11: app/admin/**/*.tsx files | B11: FRONTEND
A12: app/affiliate/**/*.tsx files | B12: FRONTEND
... A46: lib/websocket/use-mt5-websocket.ts | B46: FRONTEND

Sheet SHARED FILES
A1: types/alert.ts | B1: SHARING
A2: types/api.ts | B2: SHARING
A3: types/disbursement.ts | B3: SHARING
A4: types/dlocal.ts | B4: SHARING
A5: types/index.ts | B5: SHARING
A6: types/indicator.ts | B6: SHARING
A7: types/next-auth.d.ts | B7: SHARING
A8: types/payment.ts | B8: SHARING
A9: types/prisma-stubs.d.ts | B9: SHARING
A10: types/tier.ts | B10: SHARING
A11: types/user.ts | B11: SHARING
A12: types/watchlist.ts | B12: SHARING
